[
    {
        "code": "7491.0045",
        "name": "CREPE MAKER 2 PLATES",
        "url": "https://www.combisteel.com/en/7491-0045-crepe-maker-2-plates.html",
        "image": "https://www.combisteel.com/media/catalog/product/cache/885770f149f21cca5edd4b51c2ad35e1/7/4/7491_0045-7420.jpg",
        "image_large": "https://www.combisteel.com/media/catalog/product/cache/885770f149f21cca5edd4b51c2ad35e1/7/4/7491_0045-7420.jpg",
        "price": 26750,
        "price_currency": "Kč bez DPH",
        "price_text": "26 750 Kč",
        "specs": {
            "ean_code": 7435137845898,
            "width": 900,
            "depth": 520,
            "height": 245,
            "material": "Stainless steel",
            "parcel_ready": "No",
            "gross_weight": 44,
            "particulars": "2 stekkers",
            "voltage": 230,
            "electrical_power": "2x 3",
            "model_tabletop/_freestanding/drop-in": "Tabletop",
            "diameter": 400,
            "brand": "COMBISTEEL",
            "plug_and_play": "Yes"
        },
        "downloads": [
            {
                "label": "Exploded view 7491.0045 (2024)",
                "url": "https://www.combisteel.com/en/amfile/file/download/file/1231918/product/921/"
            },
            {
                "label": "Manual 7491.0040-0045",
                "url": "https://www.combisteel.com/en/amfile/file/download/file/1231919/product/921/"
            }
        ],
        "accessories": []
    },
    {
        "code": "7540.0015",
        "name": "MINI PANCAKE MAKER 100PCS Ø4CM",
        "url": "https://www.combisteel.com/en/7540-0015-mini-pancake-maker-100pcs-o4cm.html",
        "image": "https://www.combisteel.com/media/catalog/product/cache/885770f149f21cca5edd4b51c2ad35e1/7/5/7540_0015_1.jpg",
        "image_large": "https://www.combisteel.com/media/catalog/product/cache/885770f149f21cca5edd4b51c2ad35e1/7/5/7540_0015_1.jpg",
        "price": 20500,
        "price_currency": "Kč bez DPH",
        "price_text": "20 500 Kč",
        "specs": {
            "width": 570,
            "depth": 540,
            "height": 190,
            "material": "Stainless steel Aisi 201",
            "parcel_ready": "Yes",
            "gross_weight": 25,
            "net_weight": 23,
            "particulars": "Cast aluminium plate with a teflon non-stick coating",
            "voltage": 230,
            "frequency": "50/60",
            "electrical_power": 24,
            "model_tabletop/_freestanding/drop-in": "Tabletop",
            "dim._griddle_wxd": "Waffle size: 43x43x18mm",
            "operation": "Knob",
            "brand": "COMBISTEEL",
            "plug_and_play": "Yes"
        },
        "downloads": [
            {
                "label": "Exploded view 7540.0015 (2024)",
                "url": "https://www.combisteel.com/en/amfile/file/download/file/1216363/product/4862/"
            },
            {
                "label": "Dimensions 7540.0015",
                "url": "https://www.combisteel.com/en/amfile/file/download/file/1216364/product/4862/"
            },
            {
                "label": "Manual 7540.0005-0010-0015-0030-0035-0040-0045",
                "url": "https://www.combisteel.com/en/amfile/file/download/file/1216365/product/4862/"
            }
        ],
        "accessories": []
    },
    {
        "code": "7455.0815",
        "name": "POPCORN MACHINE INCL. WHEELS",
        "url": "https://www.combisteel.com/en/7455-0815-popcorn-machine-incl-wheels.html",
        "image": "https://www.combisteel.com/media/catalog/product/cache/885770f149f21cca5edd4b51c2ad35e1/7/4/7455_0815-5557.jpg",
        "image_large": "https://www.combisteel.com/media/catalog/product/cache/885770f149f21cca5edd4b51c2ad35e1/7/4/7455_0815-5557.jpg",
        "price": 17000,
        "price_currency": "Kč bez DPH",
        "price_text": "17 000 Kč",
        "specs": {
            "ean_code": 7435137851899,
            "width": 560,
            "depth": 417,
            "height": 1560,
            "parcel_ready": "No",
            "gross_weight": 43,
            "net_weight": 39,
            "particulars": "Hoeveelheid maïs (Gr/per keer): 150",
            "voltage": 230,
            "frequency": 50,
            "electrical_power": 1.35,
            "model_tabletop/_freestanding/drop-in": "Freestanding",
            "cycle_time": "3-5 min.",
            "brand": "COMBISTEEL",
            "cord_length": 1580,
            "plug_and_play": "Yes",
            "lights": "Yes"
        },
        "downloads": [
            {
                "label": "Exploded view 7455.0810-0815",
                "url": "https://www.combisteel.com/en/amfile/file/download/file/1215044/product/924/"
            },
            {
                "label": "EU DECLARATION OF CONFORMITY 7455.0810-0815",
                "url": "https://www.combisteel.com/en/amfile/file/download/file/1215045/product/924/"
            },
            {
                "label": "Manual 7455.0810-0815",
                "url": "https://www.combisteel.com/en/amfile/file/download/file/1215046/product/924/"
            }
        ],
        "accessories": []
    },
    {
        "code": "7491.0040",
        "name": "CREPE MAKER 1 PLATE",
        "url": "https://www.combisteel.com/en/7491-0040-crepe-maker-1-plate.html",
        "image": "https://www.combisteel.com/media/catalog/product/cache/885770f149f21cca5edd4b51c2ad35e1/7/4/7491_0040-7419.jpg",
        "image_large": "https://www.combisteel.com/media/catalog/product/cache/885770f149f21cca5edd4b51c2ad35e1/7/4/7491_0040-7419.jpg",
        "price": 14750,
        "price_currency": "Kč bez DPH",
        "price_text": "14 750 Kč",
        "specs": {
            "ean_code": 7435137845881,
            "width": 450,
            "depth": 520,
            "height": 245,
            "material": "Stainless steel",
            "parcel_ready": "Yes",
            "gross_weight": 23,
            "voltage": 230,
            "electrical_power": 3,
            "model_tabletop/_freestanding/drop-in": "Tabletop",
            "diameter": 400,
            "brand": "COMBISTEEL",
            "plug_and_play": "Yes"
        },
        "downloads": [
            {
                "label": "Manual 7491.0040-0045",
                "url": "https://www.combisteel.com/en/amfile/file/download/file/1214496/product/920/"
            }
        ],
        "accessories": []
    },
    {
        "code": "7491.0050",
        "name": "WAFFLE MAKER",
        "url": "https://www.combisteel.com/en/7491-0050-waffle-maker.html",
        "image": "https://www.combisteel.com/media/catalog/product/cache/885770f149f21cca5edd4b51c2ad35e1/7/4/7491_0050-7417.jpg",
        "image_large": "https://www.combisteel.com/media/catalog/product/cache/885770f149f21cca5edd4b51c2ad35e1/7/4/7491_0050-7417.jpg",
        "price": 13875,
        "price_currency": "Kč bez DPH",
        "price_text": "13 875 Kč",
        "specs": {
            "ean_code": 7435137846802,
            "width": 300,
            "depth": 320,
            "height": 300,
            "material": "Stainless steel",
            "color": "Stainless steel",
            "parcel_ready": "Yes",
            "gross_weight": 24,
            "voltage": 230,
            "electrical_power": 2.2,
            "model_tabletop/_freestanding/drop-in": "Tabletop",
            "dim._griddle_wxd": "2x 80x160",
            "brand": "COMBISTEEL",
            "plug_and_play": "Yes"
        },
        "downloads": [
            {
                "label": "Manual 7491.0050",
                "url": "https://www.combisteel.com/en/amfile/file/download/file/1214499/product/922/"
            },
            {
                "label": "Exploded view - Wiring diagram 7491.0050",
                "url": "https://www.combisteel.com/en/amfile/file/download/file/1214500/product/922/"
            }
        ],
        "accessories": []
    },
    {
        "code": "7455.0800",
        "name": "CANDY FLOSS MACHINE 720",
        "url": "https://www.combisteel.com/en/7455-0800-candy-floss-machine-720.html",
        "image": "https://www.combisteel.com/media/catalog/product/cache/885770f149f21cca5edd4b51c2ad35e1/7/4/7455_0800-7122_1.jpg",
        "image_large": "https://www.combisteel.com/media/catalog/product/cache/885770f149f21cca5edd4b51c2ad35e1/7/4/7455_0800-7122_1.jpg",
        "price": 13375,
        "price_currency": "Kč bez DPH",
        "price_text": "13 375 Kč",
        "specs": {
            "ean_code": 7435137851868,
            "width": 720,
            "depth": 720,
            "height": 500,
            "parcel_ready": "No",
            "gross_weight": 168,
            "net_weight": 146,
            "voltage": 230,
            "frequency": 50,
            "electrical_power": 1.03,
            "diameter": 720,
            "cycle_time": 30,
            "brand": "COMBISTEEL",
            "cord_length": 1750,
            "plug_and_play": "Yes"
        },
        "downloads": [
            {
                "label": "EU DECLARATION OF CONFORMITY 7455.0800-0805",
                "url": "https://www.combisteel.com/en/amfile/file/download/file/1215035/product/915/"
            },
            {
                "label": "Exploded view 7455.0800 (2024)",
                "url": "https://www.combisteel.com/en/amfile/file/download/file/1215036/product/915/"
            },
            {
                "label": "Manual 7455.0800-0805",
                "url": "https://www.combisteel.com/en/amfile/file/download/file/1215037/product/915/"
            }
        ],
        "accessories": [
            {
                "code": "7455.0830",
                "name": "COVER FOR CANDY FLOSS MACHINE 720",
                "url": "https://www.combisteel.com/en/7455-0830-cover-for-candy-floss-machine-720.html",
                "image": "https://www.combisteel.com/media/catalog/product/cache/885770f149f21cca5edd4b51c2ad35e1/7/4/7455_0830-7121.jpg",
                "image_large": "https://www.combisteel.com/media/catalog/product/cache/885770f149f21cca5edd4b51c2ad35e1/7/4/7455_0830-7121.jpg",
                "price": 5000,
                "price_currency": "Kč bez DPH",
                "price_text": "5 000 Kč"
            }
        ]
    },
    {
        "code": "7455.0805",
        "name": "CANDY FLOSS MACHINE 520",
        "url": "https://www.combisteel.com/en/7455-0805-candy-floss-machine-520.html",
        "image": "https://www.combisteel.com/media/catalog/product/cache/885770f149f21cca5edd4b51c2ad35e1/7/4/7455_0805_2-min_1.png",
        "image_large": "https://www.combisteel.com/media/catalog/product/cache/885770f149f21cca5edd4b51c2ad35e1/7/4/7455_0805_2-min_1.png",
        "price": 10875,
        "price_currency": "Kč bez DPH",
        "price_text": "10 875 Kč",
        "specs": {
            "ean_code": 7435137851875,
            "width": 520,
            "depth": 520,
            "height": 500,
            "parcel_ready": "Yes",
            "gross_weight": 146,
            "net_weight": 11,
            "voltage": 230,
            "frequency": 50,
            "electrical_power": 1.03,
            "diameter": 520,
            "cycle_time": 30,
            "brand": "COMBISTEEL",
            "cord_length": 1750,
            "plug_and_play": "Yes"
        },
        "downloads": [
            {
                "label": "EU DECLARATION OF CONFORMITY 7455.0800-0805",
                "url": "https://www.combisteel.com/en/amfile/file/download/file/1215038/product/917/"
            },
            {
                "label": "Exploded view 7455.0805 (2024)",
                "url": "https://www.combisteel.com/en/amfile/file/download/file/1215039/product/917/"
            },
            {
                "label": "Manual 7455.0800-0805",
                "url": "https://www.combisteel.com/en/amfile/file/download/file/1215040/product/917/"
            }
        ],
        "accessories": [
            {
                "code": "7455.0825",
                "name": "COVER FOR CANDY FLOSS MACHINE 520",
                "url": "https://www.combisteel.com/en/7455-0825-cover-for-candy-floss-machine-520.html",
                "image": "https://www.combisteel.com/media/catalog/product/cache/885770f149f21cca5edd4b51c2ad35e1/7/4/7455_0825-7121.jpg",
                "image_large": "https://www.combisteel.com/media/catalog/product/cache/885770f149f21cca5edd4b51c2ad35e1/7/4/7455_0825-7121.jpg",
                "price": 2250,
                "price_currency": "Kč bez DPH",
                "price_text": "2 250 Kč"
            }
        ]
    },
    {
        "code": "7540.0010",
        "name": "MINI PANCAKE MAKER 50PCS Ø4,3CM",
        "url": "https://www.combisteel.com/en/7540-0010-mini-pancake-maker-50pcs-o4-3cm.html",
        "image": "https://www.combisteel.com/media/catalog/product/cache/885770f149f21cca5edd4b51c2ad35e1/7/5/7540_0010_1.jpg",
        "image_large": "https://www.combisteel.com/media/catalog/product/cache/885770f149f21cca5edd4b51c2ad35e1/7/5/7540_0010_1.jpg",
        "price": 10375,
        "price_currency": "Kč bez DPH",
        "price_text": "10 375 Kč",
        "specs": {
            "width": 540,
            "depth": 335,
            "height": 200,
            "material": "Stainless steel Aisi 201",
            "parcel_ready": "Yes",
            "gross_weight": 13,
            "net_weight": 10,
            "particulars": "Cast aluminium plate with a teflon non-stick coating",
            "voltage": 230,
            "frequency": "50/60",
            "electrical_power": 18,
            "model_tabletop/_freestanding/drop-in": "Tabletop",
            "dim._griddle_wxd": "Waffle size: 43x43x18mm",
            "operation": "Knob",
            "brand": "COMBISTEEL",
            "plug_and_play": "Yes"
        },
        "downloads": [
            {
                "label": "Exploded view 7540.0010 (2024)",
                "url": "https://www.combisteel.com/en/amfile/file/download/file/1224225/product/4861/"
            },
            {
                "label": "Dimensions 7540.0010",
                "url": "https://www.combisteel.com/en/amfile/file/download/file/1224226/product/4861/"
            },
            {
                "label": "Manual 7540.0005-0010-0015-0030-0035-0040-0045",
                "url": "https://www.combisteel.com/en/amfile/file/download/file/1224227/product/4861/"
            }
        ],
        "accessories": []
    },
    {
        "code": "7455.0810",
        "name": "POPCORN MACHINE",
        "url": "https://www.combisteel.com/en/7455-0810-popcorn-machine.html",
        "image": "https://www.combisteel.com/media/catalog/product/cache/885770f149f21cca5edd4b51c2ad35e1/7/4/7455_0810_2-min_1.png",
        "image_large": "https://www.combisteel.com/media/catalog/product/cache/885770f149f21cca5edd4b51c2ad35e1/7/4/7455_0810_2-min_1.png",
        "price": 9975,
        "price_currency": "Kč bez DPH",
        "price_text": "9 975 Kč",
        "specs": {
            "ean_code": 7435137851882,
            "width": 560,
            "depth": 417,
            "height": 770,
            "parcel_ready": "No",
            "gross_weight": 255,
            "net_weight": 23,
            "particulars": "Hoeveelheid maïs (Gr/per keer): 150",
            "voltage": 230,
            "frequency": 50,
            "electrical_power": 1.35,
            "model_tabletop/_freestanding/drop-in": "Tabletop",
            "cycle_time": "3-5 min.",
            "brand": "COMBISTEEL",
            "cord_length": 1580,
            "plug_and_play": "Yes",
            "lights": "Yes"
        },
        "downloads": [
            {
                "label": "Exploded view 7455.0810-0815",
                "url": "https://www.combisteel.com/en/amfile/file/download/file/1224276/product/923/"
            },
            {
                "label": "EU DECLARATION OF CONFORMITY 7455.0810-0815",
                "url": "https://www.combisteel.com/en/amfile/file/download/file/1224277/product/923/"
            },
            {
                "label": "Manual 7455.0810-0815",
                "url": "https://www.combisteel.com/en/amfile/file/download/file/1224278/product/923/"
            }
        ],
        "accessories": []
    },
    {
        "code": "7540.0035",
        "name": "PANCAKE MAKER 9PCS - AMERICAN - Ø7.5CM",
        "url": "https://www.combisteel.com/en/7540-0035-pancake-maker-9pcs-american-o7-5cm.html",
        "image": "https://www.combisteel.com/media/catalog/product/cache/885770f149f21cca5edd4b51c2ad35e1/7/5/7540_0035_1.jpg",
        "image_large": "https://www.combisteel.com/media/catalog/product/cache/885770f149f21cca5edd4b51c2ad35e1/7/5/7540_0035_1.jpg",
        "price": 9875,
        "price_currency": "Kč bez DPH",
        "price_text": "9 875 Kč",
        "specs": {
            "width": 305,
            "depth": 430,
            "height": 505,
            "material": "Stainless steel Aisi 201",
            "parcel_ready": "Yes",
            "gross_weight": 13,
            "net_weight": 10,
            "particulars": "Cast aluminium plate with a teflon non-stick coating",
            "voltage": 230,
            "frequency": 50,
            "electrical_power": 175,
            "model_tabletop/_freestanding/drop-in": "Tabletop",
            "dim._griddle_wxd": "Waffle size: 78x78x20mm",
            "operation": "Knob",
            "brand": "COMBISTEEL",
            "plug_and_play": "Yes"
        },
        "downloads": [
            {
                "label": "Exploded view 7540.0035 (2024)",
                "url": "https://www.combisteel.com/en/amfile/file/download/file/1216367/product/4866/"
            },
            {
                "label": "Dimensions 7540.0035",
                "url": "https://www.combisteel.com/en/amfile/file/download/file/1216368/product/4866/"
            },
            {
                "label": "Manual 7540.0005-0010-0015-0030-0035-0040-0045",
                "url": "https://www.combisteel.com/en/amfile/file/download/file/1216369/product/4866/"
            }
        ],
        "accessories": []
    },
    {
        "code": "7540.0090",
        "name": "WAFFLE IRON 4PCS PINE TREE LOLLIPOP",
        "url": "https://www.combisteel.com/en/7540-0090-waffle-iron-4pcs-pine-tree-lollipop.html",
        "image": "https://www.combisteel.com/media/catalog/product/cache/885770f149f21cca5edd4b51c2ad35e1/7/5/7540_0090_1.jpg",
        "image_large": "https://www.combisteel.com/media/catalog/product/cache/885770f149f21cca5edd4b51c2ad35e1/7/5/7540_0090_1.jpg",
        "price": 9875,
        "price_currency": "Kč bez DPH",
        "price_text": "9 875 Kč",
        "specs": {
            "width": 305,
            "depth": 430,
            "height": 505,
            "material": "Stainless steel Aisi 201",
            "parcel_ready": "Yes",
            "gross_weight": 14,
            "net_weight": 12,
            "particulars": "Cast aluminium plate with a teflon non-stick coating",
            "voltage": 230,
            "frequency": 50,
            "electrical_power": 175,
            "model_tabletop/_freestanding/drop-in": "Tabletop",
            "dim._griddle_wxd": "Waffle size: 223x52x40mm",
            "operation": "Knob",
            "brand": "COMBISTEEL",
            "plug_and_play": "Yes"
        },
        "downloads": [
            {
                "label": "Exploded view 7540.0090 (2024)",
                "url": "https://www.combisteel.com/en/amfile/file/download/file/1216408/product/4877/"
            },
            {
                "label": "Dimensions 7540.0090",
                "url": "https://www.combisteel.com/en/amfile/file/download/file/1216409/product/4877/"
            },
            {
                "label": "Manual 7540.0090",
                "url": "https://www.combisteel.com/en/amfile/file/download/file/1216410/product/4877/"
            }
        ],
        "accessories": []
    },
    {
        "code": "7518.0180",
        "name": "NACHO WARMER.",
        "url": "https://www.combisteel.com/en/7518-0180-nacho-warmer.html",
        "image": "https://www.combisteel.com/media/catalog/product/cache/885770f149f21cca5edd4b51c2ad35e1/7/5/7518_0180_1_1.jpg",
        "image_large": "https://www.combisteel.com/media/catalog/product/cache/885770f149f21cca5edd4b51c2ad35e1/7/5/7518_0180_1_1.jpg",
        "price": 9500,
        "price_currency": "Kč bez DPH",
        "price_text": "9 500 Kč",
        "specs": {
            "width": 462,
            "depth": 365,
            "height": 588,
            "material": "Hardglas",
            "color": "Black",
            "parcel_ready": "No",
            "gross_weight": 177,
            "net_weight": 16,
            "voltage": 230,
            "frequency": 50,
            "electrical_power": 19,
            "model_tabletop/_freestanding/drop-in": "Tabletop",
            "cycle_time": "4 minutes",
            "brand": "COMBISTEEL",
            "plug_and_play": "Yes",
            "lights": "Yes"
        },
        "downloads": [
            {
                "label": "Manual 7518.0180",
                "url": "https://www.combisteel.com/en/amfile/file/download/file/1216469/product/4852/"
            },
            {
                "label": "7518.0180 dimensions",
                "url": "https://www.combisteel.com/en/amfile/file/download/file/1216470/product/4852/"
            }
        ],
        "accessories": []
    },
    {
        "code": "7540.0030",
        "name": "PANCAKE MAKER 4PCS - AMERICAN - Ø10CM",
        "url": "https://www.combisteel.com/en/7540-0030-pancake-maker-4pcs-american-o10cm.html",
        "image": "https://www.combisteel.com/media/catalog/product/cache/885770f149f21cca5edd4b51c2ad35e1/7/5/7540_0030_1.jpg",
        "image_large": "https://www.combisteel.com/media/catalog/product/cache/885770f149f21cca5edd4b51c2ad35e1/7/5/7540_0030_1.jpg",
        "price": 9000,
        "price_currency": "Kč bez DPH",
        "price_text": "9 000 Kč",
        "specs": {
            "width": 305,
            "depth": 430,
            "height": 505,
            "material": "Stainless steel Aisi 201",
            "parcel_ready": "Yes",
            "gross_weight": 13,
            "net_weight": 11,
            "particulars": "Cast aluminium plate with a teflon non-stick coating",
            "voltage": 230,
            "frequency": 50,
            "electrical_power": 165,
            "model_tabletop/_freestanding/drop-in": "Tabletop",
            "dim._griddle_wxd": "Waffle size: 98x98x20mm",
            "operation": "Knob",
            "brand": "COMBISTEEL",
            "plug_and_play": "Yes"
        },
        "downloads": [
            {
                "label": "Dimensions 7540.0030",
                "url": "https://www.combisteel.com/en/amfile/file/download/file/1216361/product/4865/"
            },
            {
                "label": "Manual 7540.0005-0010-0015-0030-0035-0040-0045",
                "url": "https://www.combisteel.com/en/amfile/file/download/file/1216362/product/4865/"
            }
        ],
        "accessories": []
    },
    {
        "code": "7540.0070",
        "name": "ROTATING WAFFLE IRON 2PCS BRUSSELS WAFFLE",
        "url": "https://www.combisteel.com/en/7540-0070-rotating-waffle-iron-2pcs-brussels-waffle.html",
        "image": "https://www.combisteel.com/media/catalog/product/cache/885770f149f21cca5edd4b51c2ad35e1/g/e/get-image-thumbnail_8.jpg",
        "image_large": "https://www.combisteel.com/media/catalog/product/cache/885770f149f21cca5edd4b51c2ad35e1/g/e/get-image-thumbnail_8.jpg",
        "price": 9000,
        "price_currency": "Kč bez DPH",
        "price_text": "9 000 Kč",
        "specs": {
            "width": 605,
            "depth": 280,
            "height": 250,
            "material": "Stainless steel Aisi 201",
            "parcel_ready": "Yes",
            "gross_weight": 14,
            "net_weight": 12,
            "particulars": "Cast aluminium plate with a teflon non-stick coating",
            "voltage": 230,
            "frequency": 50,
            "electrical_power": 12,
            "model_tabletop/_freestanding/drop-in": "Tabletop",
            "dim._griddle_wxd": "Waffle size: 167x102x28mm",
            "operation": "Knob",
            "brand": "COMBISTEEL",
            "plug_and_play": "Yes"
        },
        "downloads": [
            {
                "label": "Exploded view 7540.0070 (2024)",
                "url": "https://www.combisteel.com/en/amfile/file/download/file/1216382/product/4874/"
            },
            {
                "label": "Dimensions 7540.0070",
                "url": "https://www.combisteel.com/en/amfile/file/download/file/1216383/product/4874/"
            },
            {
                "label": "Manual 7540.0050-0055-0060-0065-0070-0075-0080-0085-0095-0100-0105",
                "url": "https://www.combisteel.com/en/amfile/file/download/file/1216384/product/4874/"
            }
        ],
        "accessories": []
    },
    {
        "code": "7540.0075",
        "name": "ROTATING WAFFLE IRON 4PCS BRUSSELS WAFFLE",
        "url": "https://www.combisteel.com/en/7540-0075-rotating-waffle-iron-4pcs-brussels-waffle.html",
        "image": "https://www.combisteel.com/media/catalog/product/cache/885770f149f21cca5edd4b51c2ad35e1/g/e/get-image-thumbnail__1__5.jpeg",
        "image_large": "https://www.combisteel.com/media/catalog/product/cache/885770f149f21cca5edd4b51c2ad35e1/g/e/get-image-thumbnail__1__5.jpeg",
        "price": 8875,
        "price_currency": "Kč bez DPH",
        "price_text": "8 875 Kč",
        "specs": {
            "width": 605,
            "depth": 280,
            "height": 250,
            "material": "Stainless steel Aisi 201",
            "parcel_ready": "Yes",
            "gross_weight": 14,
            "net_weight": 11,
            "particulars": "Cast aluminium plate with a teflon non-stick coating",
            "voltage": 230,
            "frequency": 50,
            "electrical_power": 12,
            "model_tabletop/_freestanding/drop-in": "Tabletop",
            "dim._griddle_wxd": "Waffle size: 88x88x26mm",
            "operation": "Knob",
            "brand": "COMBISTEEL",
            "plug_and_play": "Yes"
        },
        "downloads": [
            {
                "label": "Exploded view 7540.0075 (2024)",
                "url": "https://www.combisteel.com/en/amfile/file/download/file/1216394/product/4873/"
            },
            {
                "label": "Dimensions 7540.0075",
                "url": "https://www.combisteel.com/en/amfile/file/download/file/1216395/product/4873/"
            },
            {
                "label": "Manual 7540.0050-0055-0060-0065-0070-0075-0080-0085-0095-0100-0105",
                "url": "https://www.combisteel.com/en/amfile/file/download/file/1216396/product/4873/"
            }
        ],
        "accessories": []
    },
    {
        "code": "7540.0105",
        "name": "WAFFLE IRON 10PCS CHURROS",
        "url": "https://www.combisteel.com/en/7540-0105-waffle-iron-10pcs-churros.html",
        "image": "https://www.combisteel.com/media/catalog/product/cache/885770f149f21cca5edd4b51c2ad35e1/7/5/7540_0105_1.jpg",
        "image_large": "https://www.combisteel.com/media/catalog/product/cache/885770f149f21cca5edd4b51c2ad35e1/7/5/7540_0105_1.jpg",
        "price": 8875,
        "price_currency": "Kč bez DPH",
        "price_text": "8 875 Kč",
        "specs": {
            "width": 302,
            "depth": 405,
            "height": 485,
            "material": "Stainless steel Aisi 201",
            "parcel_ready": "Yes",
            "gross_weight": 13,
            "net_weight": 10,
            "particulars": "Cast aluminium plate with a teflon non-stick coating",
            "voltage": 230,
            "frequency": 50,
            "electrical_power": 175,
            "model_tabletop/_freestanding/drop-in": "Tabletop",
            "dim._griddle_wxd": "Waffle size: 217x19x15mm",
            "operation": "Knob",
            "brand": "COMBISTEEL",
            "plug_and_play": "Yes"
        },
        "downloads": [
            {
                "label": "Dimensions 7540.0105",
                "url": "https://www.combisteel.com/en/amfile/file/download/file/1216411/product/4880/"
            },
            {
                "label": "Manual 7540.0050-0055-0060-0065-0070-0075-0080-0085-0095-0100-0105",
                "url": "https://www.combisteel.com/en/amfile/file/download/file/1216412/product/4880/"
            }
        ],
        "accessories": []
    },
    {
        "code": "7540.0045",
        "name": "SYRUP WAFFLE MAKER ROUND",
        "url": "https://www.combisteel.com/en/7540-0045-syrup-waffle-maker-round.html",
        "image": "https://www.combisteel.com/media/catalog/product/cache/885770f149f21cca5edd4b51c2ad35e1/7/5/7540_0045_1.jpg",
        "image_large": "https://www.combisteel.com/media/catalog/product/cache/885770f149f21cca5edd4b51c2ad35e1/7/5/7540_0045_1.jpg",
        "price": 7875,
        "price_currency": "Kč bez DPH",
        "price_text": "7 875 Kč",
        "specs": {
            "width": 305,
            "depth": 430,
            "height": 505,
            "material": "Stainless steel Aisi 201",
            "parcel_ready": "Yes",
            "gross_weight": 13,
            "net_weight": 10,
            "particulars": "Cast aluminium plate with a teflon non-stick coating",
            "voltage": 230,
            "frequency": 50,
            "electrical_power": 175,
            "model_tabletop/_freestanding/drop-in": "Tabletop",
            "dim._griddle_wxd": "Waffle size: 250x250x3mm",
            "operation": "Knob",
            "brand": "COMBISTEEL",
            "plug_and_play": "Yes"
        },
        "downloads": [
            {
                "label": "Exploded view 7540.0045 (2024)",
                "url": "https://www.combisteel.com/en/amfile/file/download/file/1216391/product/4867/"
            },
            {
                "label": "Dimensions 7540.0045",
                "url": "https://www.combisteel.com/en/amfile/file/download/file/1216392/product/4867/"
            },
            {
                "label": "Manual 7540.0005-0010-0015-0030-0035-0040-0045",
                "url": "https://www.combisteel.com/en/amfile/file/download/file/1216393/product/4867/"
            }
        ],
        "accessories": []
    },
    {
        "code": "7540.0040",
        "name": "SYRUP WAFFLE MAKER SQUARED",
        "url": "https://www.combisteel.com/en/7540-0040-syrup-waffle-maker-squared.html",
        "image": "https://www.combisteel.com/media/catalog/product/cache/885770f149f21cca5edd4b51c2ad35e1/7/5/7540_0040_1.jpg",
        "image_large": "https://www.combisteel.com/media/catalog/product/cache/885770f149f21cca5edd4b51c2ad35e1/7/5/7540_0040_1.jpg",
        "price": 7875,
        "price_currency": "Kč bez DPH",
        "price_text": "7 875 Kč",
        "specs": {
            "width": 305,
            "depth": 430,
            "height": 505,
            "material": "Stainless steel Aisi 201",
            "parcel_ready": "Yes",
            "gross_weight": 13,
            "net_weight": 95,
            "particulars": "Cast aluminium plate with a teflon non-stick coating",
            "voltage": 230,
            "frequency": 50,
            "electrical_power": 175,
            "model_tabletop/_freestanding/drop-in": "Tabletop",
            "dim._griddle_wxd": "Waffle size: 253x253x3mm",
            "operation": "Knob",
            "brand": "COMBISTEEL",
            "plug_and_play": "Yes"
        },
        "downloads": [
            {
                "label": "Exploded view 7540.0040 (2024)",
                "url": "https://www.combisteel.com/en/amfile/file/download/file/1216373/product/4868/"
            },
            {
                "label": "Dimensions 7540.0040",
                "url": "https://www.combisteel.com/en/amfile/file/download/file/1216374/product/4868/"
            },
            {
                "label": "Manual 7540.0005-0010-0015-0030-0035-0040-0045",
                "url": "https://www.combisteel.com/en/amfile/file/download/file/1216375/product/4868/"
            }
        ],
        "accessories": []
    },
    {
        "code": "7540.0055",
        "name": "WAFFLE IRON 2PCS BRUSSELS WAFFLE",
        "url": "https://www.combisteel.com/en/7540-0055-waffle-iron-2pcs-brussels-waffle.html",
        "image": "https://www.combisteel.com/media/catalog/product/cache/885770f149f21cca5edd4b51c2ad35e1/7/5/7540_0055_1.jpg",
        "image_large": "https://www.combisteel.com/media/catalog/product/cache/885770f149f21cca5edd4b51c2ad35e1/7/5/7540_0055_1.jpg",
        "price": 7875,
        "price_currency": "Kč bez DPH",
        "price_text": "7 875 Kč",
        "specs": {
            "width": 305,
            "depth": 430,
            "height": 505,
            "material": "Stainless steel Aisi 201",
            "parcel_ready": "Yes",
            "gross_weight": 105,
            "net_weight": 85,
            "particulars": "Cast aluminium plate with a teflon non-stick coating",
            "voltage": 230,
            "frequency": 50,
            "electrical_power": 175,
            "model_tabletop/_freestanding/drop-in": "Tabletop",
            "dim._griddle_wxd": "Waffle size: 162x98x24mm",
            "operation": "Knob",
            "brand": "COMBISTEEL",
            "plug_and_play": "Yes"
        },
        "downloads": [
            {
                "label": "Exploded view 7540.0055 (2024)",
                "url": "https://www.combisteel.com/en/amfile/file/download/file/1216385/product/4872/"
            },
            {
                "label": "Dimensions 7540.0055",
                "url": "https://www.combisteel.com/en/amfile/file/download/file/1216386/product/4872/"
            },
            {
                "label": "Manual 7540.0050-0055-0060-0065-0070-0075-0080-0085-0095-0100-0105",
                "url": "https://www.combisteel.com/en/amfile/file/download/file/1216387/product/4872/"
            }
        ],
        "accessories": []
    },
    {
        "code": "7540.0080",
        "name": "WAFFLE IRON 4PCS ROUND WAFFLES",
        "url": "https://www.combisteel.com/en/7540-0080-waffle-iron-4pcs-round-waffles.html",
        "image": "https://www.combisteel.com/media/catalog/product/cache/885770f149f21cca5edd4b51c2ad35e1/7/5/7540_0080_1.jpg",
        "image_large": "https://www.combisteel.com/media/catalog/product/cache/885770f149f21cca5edd4b51c2ad35e1/7/5/7540_0080_1.jpg",
        "price": 7875,
        "price_currency": "Kč bez DPH",
        "price_text": "7 875 Kč",
        "specs": {
            "width": 305,
            "depth": 430,
            "height": 505,
            "material": "Stainless steel Aisi 201",
            "parcel_ready": "Yes",
            "gross_weight": 13,
            "net_weight": 10,
            "particulars": "Cast aluminium plate with a teflon non-stick coating",
            "voltage": 230,
            "frequency": 50,
            "electrical_power": 175,
            "model_tabletop/_freestanding/drop-in": "Tabletop",
            "dim._griddle_wxd": "Waffle size:112x112x16mm",
            "operation": "Knob",
            "brand": "COMBISTEEL",
            "plug_and_play": "Yes"
        },
        "downloads": [
            {
                "label": "Exploded view 7540.0080 (2024)",
                "url": "https://www.combisteel.com/en/amfile/file/download/file/1216397/product/4875/"
            },
            {
                "label": "Dimensions 7540.0080",
                "url": "https://www.combisteel.com/en/amfile/file/download/file/1216398/product/4875/"
            },
            {
                "label": "Manual 7540.0050-0055-0060-0065-0070-0075-0080-0085-0095-0100-0105",
                "url": "https://www.combisteel.com/en/amfile/file/download/file/1216399/product/4875/"
            }
        ],
        "accessories": []
    },
    {
        "code": "7540.0085",
        "name": "WAFFLE IRON 4PCS SQUARE WAFFLES",
        "url": "https://www.combisteel.com/en/7540-0085-waffle-iron-4pcs-square-waffles.html",
        "image": "https://www.combisteel.com/media/catalog/product/cache/885770f149f21cca5edd4b51c2ad35e1/7/5/7540_0085_1.jpg",
        "image_large": "https://www.combisteel.com/media/catalog/product/cache/885770f149f21cca5edd4b51c2ad35e1/7/5/7540_0085_1.jpg",
        "price": 7875,
        "price_currency": "Kč bez DPH",
        "price_text": "7 875 Kč",
        "specs": {
            "width": 305,
            "depth": 430,
            "height": 505,
            "material": "Stainless steel Aisi 201",
            "parcel_ready": "Yes",
            "gross_weight": 13,
            "net_weight": 10,
            "particulars": "Cast aluminium plate with a teflon non-stick coating",
            "voltage": 230,
            "frequency": "50/60",
            "electrical_power": 175,
            "model_tabletop/_freestanding/drop-in": "Tabletop",
            "dim._griddle_wxd": "Waffle size: 113x113x16mm",
            "operation": "Knob",
            "brand": "COMBISTEEL",
            "plug_and_play": "Yes"
        },
        "downloads": [
            {
                "label": "Dimensions 7540.0085",
                "url": "https://www.combisteel.com/en/amfile/file/download/file/1216400/product/4876/"
            },
            {
                "label": "Manual 7540.0050-0055-0060-0065-0070-0075-0080-0085-0095-0100-0105",
                "url": "https://www.combisteel.com/en/amfile/file/download/file/1216401/product/4876/"
            }
        ],
        "accessories": []
    },
    {
        "code": "7540.0100",
        "name": "WAFFLE IRON 7PCS CHURROS",
        "url": "https://www.combisteel.com/en/7540-0100-waffle-iron-7pcs-churros.html",
        "image": "https://www.combisteel.com/media/catalog/product/cache/885770f149f21cca5edd4b51c2ad35e1/7/5/7540_0100_1.jpg",
        "image_large": "https://www.combisteel.com/media/catalog/product/cache/885770f149f21cca5edd4b51c2ad35e1/7/5/7540_0100_1.jpg",
        "price": 7750,
        "price_currency": "Kč bez DPH",
        "price_text": "7 750 Kč",
        "specs": {
            "width": 305,
            "depth": 430,
            "height": 505,
            "material": "Stainless steel Aisi 201",
            "parcel_ready": "Yes",
            "gross_weight": 13,
            "net_weight": 85,
            "particulars": "Cast aluminium plate with a teflon non-stick coating",
            "voltage": 230,
            "frequency": 50,
            "electrical_power": 175,
            "model_tabletop/_freestanding/drop-in": "Tabletop",
            "dim._griddle_wxd": "Waffle size: 234x22x20mm",
            "operation": "Knob",
            "brand": "COMBISTEEL",
            "plug_and_play": "Yes"
        },
        "downloads": [
            {
                "label": "Exploded view 7540.0100 (2024)",
                "url": "https://www.combisteel.com/en/amfile/file/download/file/1216405/product/4879/"
            },
            {
                "label": "Dimensions 7540.0100",
                "url": "https://www.combisteel.com/en/amfile/file/download/file/1216406/product/4879/"
            },
            {
                "label": "Manual 7540.0050-0055-0060-0065-0070-0075-0080-0085-0095-0100-0105",
                "url": "https://www.combisteel.com/en/amfile/file/download/file/1216407/product/4879/"
            }
        ],
        "accessories": []
    },
    {
        "code": "7518.0165",
        "name": "CRÊPE MAKER",
        "url": "https://www.combisteel.com/en/7518-0165-crepe-maker.html",
        "image": "https://www.combisteel.com/media/catalog/product/cache/885770f149f21cca5edd4b51c2ad35e1/7/5/7518_0165_1_1.jpg",
        "image_large": "https://www.combisteel.com/media/catalog/product/cache/885770f149f21cca5edd4b51c2ad35e1/7/5/7518_0165_1_1.jpg",
        "price": 7750,
        "price_currency": "Kč bez DPH",
        "price_text": "7 750 Kč",
        "specs": {
            "width": 400,
            "depth": 400,
            "height": 178,
            "material": "Stainless steel Aisi 201",
            "accessories_included": "Wooden spatula",
            "parcel_ready": "Yes",
            "gross_weight": 167,
            "net_weight": 157,
            "particulars": "Cast iron plate with Teflon coating",
            "voltage": 230,
            "electrical_power": 3,
            "model_tabletop/_freestanding/drop-in": "Tabletop",
            "diameter": 400,
            "brand": "COMBISTEEL",
            "temperature_range": "+50/+300",
            "plug_and_play": "Yes"
        },
        "downloads": [
            {
                "label": "Manual 7518.0165",
                "url": "https://www.combisteel.com/en/amfile/file/download/file/1224979/product/4855/"
            },
            {
                "label": "7518.0165 dimensions",
                "url": "https://www.combisteel.com/en/amfile/file/download/file/1224980/product/4855/"
            }
        ],
        "accessories": []
    },
    {
        "code": "7455.1620",
        "name": "WAFFLE MAKER",
        "url": "https://www.combisteel.com/en/7455-1620-waffle-maker.html",
        "image": "https://www.combisteel.com/media/catalog/product/cache/885770f149f21cca5edd4b51c2ad35e1/7/4/7455_1620-6259.jpg",
        "image_large": "https://www.combisteel.com/media/catalog/product/cache/885770f149f21cca5edd4b51c2ad35e1/7/4/7455_1620-6259.jpg",
        "price": 7750,
        "price_currency": "Kč bez DPH",
        "price_text": "7 750 Kč",
        "specs": {
            "ean_code": 7435137846895,
            "width": 300,
            "depth": 450,
            "height": 250,
            "material": "Stainless steel",
            "color": "Stainless steel",
            "parcel_ready": "Yes",
            "gross_weight": 11,
            "net_weight": 10,
            "voltage": 230,
            "electrical_power": 2,
            "model_tabletop/_freestanding/drop-in": "Tabletop",
            "dim._griddle_wxd": "240x240",
            "brand": "COMBISTEEL",
            "temperature_range": "+50/+300",
            "plug_and_play": "Yes"
        },
        "downloads": [
            {
                "label": "Exploded view 7455.1620 (2020)",
                "url": "https://www.combisteel.com/en/amfile/file/download/file/1225909/product/919/"
            },
            {
                "label": "EU DECLARATION OF CONFORMITY 7455.1620",
                "url": "https://www.combisteel.com/en/amfile/file/download/file/1225910/product/919/"
            },
            {
                "label": "Manual 7455.1620",
                "url": "https://www.combisteel.com/en/amfile/file/download/file/1225911/product/919/"
            }
        ],
        "accessories": []
    },
    {
        "code": "7540.0095",
        "name": "WAFFLE IRON 5PCS CHURROS",
        "url": "https://www.combisteel.com/en/7540-0095-waffle-iron-5pcs-churros.html",
        "image": "https://www.combisteel.com/media/catalog/product/cache/885770f149f21cca5edd4b51c2ad35e1/7/5/7540_0095_1.jpg",
        "image_large": "https://www.combisteel.com/media/catalog/product/cache/885770f149f21cca5edd4b51c2ad35e1/7/5/7540_0095_1.jpg",
        "price": 7500,
        "price_currency": "Kč bez DPH",
        "price_text": "7 500 Kč",
        "specs": {
            "width": 380,
            "depth": 350,
            "height": 465,
            "material": "Stainless steel Aisi 201",
            "parcel_ready": "Yes",
            "gross_weight": 13,
            "net_weight": 12,
            "particulars": "Cast aluminium plate with a teflon non-stick coating",
            "voltage": 230,
            "frequency": 50,
            "electrical_power": 175,
            "model_tabletop/_freestanding/drop-in": "Tabletop",
            "dim._griddle_wxd": "Waffle size: 297x22x20mm",
            "operation": "Knob",
            "brand": "COMBISTEEL",
            "plug_and_play": "Yes"
        },
        "downloads": [
            {
                "label": "Exploded view 7540.0095 (2024)",
                "url": "https://www.combisteel.com/en/amfile/file/download/file/1216402/product/4878/"
            },
            {
                "label": "Dimensions 7540.0095",
                "url": "https://www.combisteel.com/en/amfile/file/download/file/1216403/product/4878/"
            },
            {
                "label": "Manual 7540.0050-0055-0060-0065-0070-0075-0080-0085-0095-0100-0105",
                "url": "https://www.combisteel.com/en/amfile/file/download/file/1216404/product/4878/"
            }
        ],
        "accessories": []
    },
    {
        "code": "7540.0060",
        "name": "WAFFLE IRON 3PCS BRUSSELS WAFFLE",
        "url": "https://www.combisteel.com/en/7540-0060-waffle-iron-3pcs-brussels-waffle.html",
        "image": "https://www.combisteel.com/media/catalog/product/cache/885770f149f21cca5edd4b51c2ad35e1/7/5/7540_0060_1.jpg",
        "image_large": "https://www.combisteel.com/media/catalog/product/cache/885770f149f21cca5edd4b51c2ad35e1/7/5/7540_0060_1.jpg",
        "price": 6375,
        "price_currency": "Kč bez DPH",
        "price_text": "6 375 Kč",
        "specs": {
            "width": 380,
            "depth": 350,
            "height": 465,
            "material": "Stainless steel Aisi 201",
            "parcel_ready": "Yes",
            "gross_weight": 13,
            "net_weight": 11,
            "particulars": "Cast aluminium plate with a teflon non-stick coating",
            "voltage": 230,
            "frequency": 50,
            "electrical_power": 175,
            "model_tabletop/_freestanding/drop-in": "Tabletop",
            "dim._griddle_wxd": "Waffle size: 125x77x22mm",
            "operation": "Knob",
            "brand": "COMBISTEEL",
            "plug_and_play": "Yes"
        },
        "downloads": [
            {
                "label": "Exploded view 7540.0060 (2024)",
                "url": "https://www.combisteel.com/en/amfile/file/download/file/1216388/product/4870/"
            },
            {
                "label": "Dimensions 7540.0060",
                "url": "https://www.combisteel.com/en/amfile/file/download/file/1216389/product/4870/"
            },
            {
                "label": "Manual 7540.0050-0055-0060-0065-0070-0075-0080-0085-0095-0100-0105",
                "url": "https://www.combisteel.com/en/amfile/file/download/file/1216390/product/4870/"
            }
        ],
        "accessories": []
    },
    {
        "code": "7540.0065",
        "name": "WAFFLE IRON 10PCS BRUSSELS WAFFLE",
        "url": "https://www.combisteel.com/en/7540-0065-waffle-iron-10pcs-brussels-waffle.html",
        "image": "https://www.combisteel.com/media/catalog/product/cache/885770f149f21cca5edd4b51c2ad35e1/7/5/7540_0065_1.jpg",
        "image_large": "https://www.combisteel.com/media/catalog/product/cache/885770f149f21cca5edd4b51c2ad35e1/7/5/7540_0065_1.jpg",
        "price": 6375,
        "price_currency": "Kč bez DPH",
        "price_text": "6 375 Kč",
        "specs": {
            "width": 380,
            "depth": 350,
            "height": 465,
            "material": "Stainless steel Aisi 201",
            "parcel_ready": "Yes",
            "gross_weight": 13,
            "net_weight": 11,
            "particulars": "Cast aluminium plate with a teflon non-stick coating",
            "voltage": 230,
            "frequency": 50,
            "electrical_power": 175,
            "model_tabletop/_freestanding/drop-in": "Tabletop",
            "dim._griddle_wxd": "Waffle size: 81x55x14",
            "operation": "Knob",
            "brand": "COMBISTEEL",
            "plug_and_play": "Yes"
        },
        "downloads": [
            {
                "label": "Exploded view 7540.0065 (2024)",
                "url": "https://www.combisteel.com/en/amfile/file/download/file/1216379/product/4871/"
            },
            {
                "label": "Dimensions 7540.0065",
                "url": "https://www.combisteel.com/en/amfile/file/download/file/1216380/product/4871/"
            },
            {
                "label": "Manual 7540.0050-0055-0060-0065-0070-0075-0080-0085-0095-0100-0105",
                "url": "https://www.combisteel.com/en/amfile/file/download/file/1216381/product/4871/"
            }
        ],
        "accessories": []
    },
    {
        "code": "7518.0125",
        "name": "HOT DOG WARMER WITH 2 BREAD HEATING STICKS",
        "url": "https://www.combisteel.com/en/7518-0125-hot-dog-warmer-with-2-bread-heating-sticks.html",
        "image": "https://www.combisteel.com/media/catalog/product/cache/885770f149f21cca5edd4b51c2ad35e1/7/5/7518_0125-13511.jpg",
        "image_large": "https://www.combisteel.com/media/catalog/product/cache/885770f149f21cca5edd4b51c2ad35e1/7/5/7518_0125-13511.jpg",
        "price": 5875,
        "price_currency": "Kč bez DPH",
        "price_text": "5 875 Kč",
        "specs": {
            "ean_code": 7422242894866,
            "width": 387,
            "depth": 300,
            "height": 395,
            "material": "Stainless steel 18/8",
            "parcel_ready": "Yes",
            "gross_weight": 72,
            "net_weight": 62,
            "particulars": "Ruimte voor hotdogs tot 240mm lang",
            "voltage": 230,
            "frequency": 50,
            "electrical_power": 5,
            "model_tabletop/_freestanding/drop-in": "Tabletop",
            "brand": "COMBISTEEL",
            "plug_and_play": "Yes"
        },
        "downloads": [
            {
                "label": "Manual 7518.0120-0125",
                "url": "https://www.combisteel.com/en/amfile/file/download/file/1215154/product/3637/"
            },
            {
                "label": "Exploded view 7518.0125 (2020)",
                "url": "https://www.combisteel.com/en/amfile/file/download/file/1215155/product/3637/"
            },
            {
                "label": "EU DECLARATION OF CONFORMITY 7518.0120-0125",
                "url": "https://www.combisteel.com/en/amfile/file/download/file/1215156/product/3637/"
            }
        ],
        "accessories": []
    },
    {
        "code": "7540.0005",
        "name": "MINI PANCAKE MAKER 25PCS Ø4,5CM",
        "url": "https://www.combisteel.com/en/7540-0005-mini-pancake-maker-25pcs-o4-5cm.html",
        "image": "https://www.combisteel.com/media/catalog/product/cache/885770f149f21cca5edd4b51c2ad35e1/7/5/7540_0005_1.jpg",
        "image_large": "https://www.combisteel.com/media/catalog/product/cache/885770f149f21cca5edd4b51c2ad35e1/7/5/7540_0005_1.jpg",
        "price": 5500,
        "price_currency": "Kč bez DPH",
        "price_text": "5 500 Kč",
        "specs": {
            "width": 300,
            "depth": 330,
            "height": 190,
            "material": "Stainless steel Aisi 201",
            "parcel_ready": "Yes",
            "gross_weight": 10,
            "net_weight": 7,
            "particulars": "Cast aluminium plate with a teflon non-stick coating",
            "voltage": 230,
            "frequency": 50,
            "electrical_power": 9,
            "model_tabletop/_freestanding/drop-in": "Tabletop",
            "dim._griddle_wxd": "Waffle size: 43x43x18mm",
            "operation": "Knob",
            "brand": "COMBISTEEL",
            "plug_and_play": "Yes"
        },
        "downloads": [
            {
                "label": "Exploded view 7540.0005 (2024)",
                "url": "https://www.combisteel.com/en/amfile/file/download/file/1216357/product/4860/"
            },
            {
                "label": "Dimensions 7540.0005",
                "url": "https://www.combisteel.com/en/amfile/file/download/file/1216358/product/4860/"
            },
            {
                "label": "Manual 7540.0005-0010-0015-0030-0035-0040-0045",
                "url": "https://www.combisteel.com/en/amfile/file/download/file/1216359/product/4860/"
            }
        ],
        "accessories": []
    },
    {
        "code": "7455.0830",
        "name": "COVER FOR CANDY FLOSS MACHINE 720",
        "url": "https://www.combisteel.com/en/7455-0830-cover-for-candy-floss-machine-720.html",
        "image": "https://www.combisteel.com/media/catalog/product/cache/885770f149f21cca5edd4b51c2ad35e1/7/4/7455_0830-7121.jpg",
        "image_large": "https://www.combisteel.com/media/catalog/product/cache/885770f149f21cca5edd4b51c2ad35e1/7/4/7455_0830-7121.jpg",
        "price": 5000,
        "price_currency": "Kč bez DPH",
        "price_text": "5 000 Kč",
        "specs": {
            "ean_code": 6017429539565,
            "width": 720,
            "depth": 720,
            "height": 360,
            "parcel_ready": "No",
            "gross_weight": 15,
            "brand": "COMBISTEEL"
        },
        "downloads": [],
        "accessories": []
    },
    {
        "code": "7518.0120",
        "name": "HOT DOG WARMER.",
        "url": "https://www.combisteel.com/en/7518-0120-hot-dog-warmer.html",
        "image": "https://www.combisteel.com/media/catalog/product/cache/885770f149f21cca5edd4b51c2ad35e1/7/5/7518_0120_1.jpg",
        "image_large": "https://www.combisteel.com/media/catalog/product/cache/885770f149f21cca5edd4b51c2ad35e1/7/5/7518_0120_1.jpg",
        "price": 4750,
        "price_currency": "Kč bez DPH",
        "price_text": "4 750 Kč",
        "specs": {
            "ean_code": 7422242894859,
            "width": 320,
            "depth": 300,
            "height": 395,
            "material": "Stainless steel 18/8",
            "parcel_ready": "Yes",
            "gross_weight": 62,
            "net_weight": 53,
            "particulars": "Ruimte voor hotdogs tot 240mm lang",
            "voltage": 230,
            "frequency": 50,
            "electrical_power": 45,
            "model_tabletop/_freestanding/drop-in": "Tabletop",
            "brand": "COMBISTEEL",
            "cord_length": 1500,
            "plug_and_play": "Yes"
        },
        "downloads": [
            {
                "label": "Manual 7518.0120-0125",
                "url": "https://www.combisteel.com/en/amfile/file/download/file/1215151/product/3636/"
            },
            {
                "label": "Exploded view 7518.0120 (2020)",
                "url": "https://www.combisteel.com/en/amfile/file/download/file/1215152/product/3636/"
            },
            {
                "label": "EU DECLARATION OF CONFORMITY 7518.0120-0125",
                "url": "https://www.combisteel.com/en/amfile/file/download/file/1215153/product/3636/"
            }
        ],
        "accessories": []
    },
    {
        "code": "7540.0050",
        "name": "WAFFLE IRON 4PCS HEART SHAPE",
        "url": "https://www.combisteel.com/en/7540-0050-waffle-iron-4pcs-heart-shape.html",
        "image": "https://www.combisteel.com/media/catalog/product/cache/885770f149f21cca5edd4b51c2ad35e1/7/5/7540_0050_1.jpg",
        "image_large": "https://www.combisteel.com/media/catalog/product/cache/885770f149f21cca5edd4b51c2ad35e1/7/5/7540_0050_1.jpg",
        "price": 4000,
        "price_currency": "Kč bez DPH",
        "price_text": "4 000 Kč",
        "specs": {
            "width": 450,
            "depth": 250,
            "height": 270,
            "material": "Stainless steel Aisi 201",
            "parcel_ready": "Yes",
            "gross_weight": 12,
            "net_weight": 9,
            "particulars": "Cast aluminium plate with a teflon non-stick coating",
            "voltage": 230,
            "frequency": 50,
            "electrical_power": 1,
            "model_tabletop/_freestanding/drop-in": "Tabletop",
            "dim._griddle_wxd": "Waffle size: 87x80x14mm",
            "operation": "Knob",
            "brand": "COMBISTEEL",
            "plug_and_play": "Yes"
        },
        "downloads": [
            {
                "label": "Exploded view 7540.0050 (2024)",
                "url": "https://www.combisteel.com/en/amfile/file/download/file/1216376/product/4869/"
            },
            {
                "label": "Dimensions 7540.0050",
                "url": "https://www.combisteel.com/en/amfile/file/download/file/1216377/product/4869/"
            },
            {
                "label": "Manual 7540.0050-0055-0060-0065-0070-0075-0080-0085-0095-0100-0105",
                "url": "https://www.combisteel.com/en/amfile/file/download/file/1216378/product/4869/"
            }
        ],
        "accessories": []
    },
    {
        "code": "7455.0825",
        "name": "COVER FOR CANDY FLOSS MACHINE 520",
        "url": "https://www.combisteel.com/en/7455-0825-cover-for-candy-floss-machine-520.html",
        "image": "https://www.combisteel.com/media/catalog/product/cache/885770f149f21cca5edd4b51c2ad35e1/7/4/7455_0825-7121.jpg",
        "image_large": "https://www.combisteel.com/media/catalog/product/cache/885770f149f21cca5edd4b51c2ad35e1/7/4/7455_0825-7121.jpg",
        "price": 2250,
        "price_currency": "Kč bez DPH",
        "price_text": "2 250 Kč",
        "specs": {
            "ean_code": 6017431622699,
            "width": 520,
            "depth": 520,
            "height": 350,
            "parcel_ready": "Yes",
            "gross_weight": 15,
            "brand": "COMBISTEEL"
        },
        "downloads": [],
        "accessories": []
    },
    {
        "code": "7540.0025",
        "name": "BATTER DISPENSER 1.6L INCL DOSING BUTTON",
        "url": "https://www.combisteel.com/en/7540-0025-batter-dispenser-1-6l-incl-dosing-button.html",
        "image": "https://www.combisteel.com/media/catalog/product/cache/885770f149f21cca5edd4b51c2ad35e1/7/5/7540_0025_correct_photo_1.jpg",
        "image_large": "https://www.combisteel.com/media/catalog/product/cache/885770f149f21cca5edd4b51c2ad35e1/7/5/7540_0025_correct_photo_1.jpg",
        "price": 1750,
        "price_currency": "Kč bez DPH",
        "price_text": "1 750 Kč",
        "specs": {
            "width": 280,
            "depth": 200,
            "height": 260,
            "material": "Stainless steel Aisi 201",
            "color": "Stainless steel",
            "parcel_ready": "Yes",
            "gross_weight": 1,
            "net_weight": 8,
            "particulars": "Spout dimensions: 3/6/8 mm",
            "brand": "COMBISTEEL"
        },
        "downloads": [
            {
                "label": "Exploded view 7540.0025 (2024)",
                "url": "https://www.combisteel.com/en/amfile/file/download/file/1216360/product/4864/"
            }
        ],
        "accessories": []
    },
    {
        "code": "7540.0020",
        "name": "BATTER DISPENSER 1.3L INCL DOSING BUTTON",
        "url": "https://www.combisteel.com/en/7540-0020-batter-dispenser-1-3l-incl-dosing-button.html",
        "image": "https://www.combisteel.com/media/catalog/product/cache/885770f149f21cca5edd4b51c2ad35e1/7/5/7540_0020_1.jpg",
        "image_large": "https://www.combisteel.com/media/catalog/product/cache/885770f149f21cca5edd4b51c2ad35e1/7/5/7540_0020_1.jpg",
        "price": 875,
        "price_currency": "Kč bez DPH",
        "price_text": "875 Kč",
        "specs": {
            "width": 260,
            "depth": 140,
            "height": 240,
            "material": "Stainless steel Aisi 201",
            "parcel_ready": "Yes",
            "gross_weight": 2,
            "net_weight": 5,
            "particulars": "Spout dimensions: 8 mm",
            "brand": "COMBISTEEL"
        },
        "downloads": [
            {
                "label": "Exploded view 7540.0020 (2024)",
                "url": "https://www.combisteel.com/en/amfile/file/download/file/1216366/product/4863/"
            }
        ],
        "accessories": []
    }
]