[
    {
        "code": "7472.0115",
        "name": "ICE CREAM DISPLAY HAWAI 16X 5LTR\n*TRANSPORT ON REQUEST*",
        "url": "https://www.combisteel.com/en/7472-0115-ice-cream-display-hawai-16x-5ltr-transport-on-request.html",
        "image": "https://www.combisteel.com/media/catalog/product/cache/885770f149f21cca5edd4b51c2ad35e1/7/4/7472_0115-6914.jpg",
        "image_large": "https://www.combisteel.com/media/catalog/product/cache/885770f149f21cca5edd4b51c2ad35e1/7/4/7472_0115-6914.jpg",
        "price": 136250,
        "price_currency": "CZK",
        "price_text": "136 250 Kč",
        "specs": {
            "ean_code": 7435137797746,
            "width": 1590,
            "depth": 1195,
            "height": 1335,
            "color": "White",
            "gross_weight": 195,
            "voltage": 230,
            "frequency": 50,
            "cooling_agent": "R 290",
            "capacity_in_units_per_time": "16x5 ltr",
            "temperature_range": "-22/-15",
            "gross_capacity": 630,
            "dim._interior_wxdxh": "1410x770x653",
            "operation": "Digital",
            "lights": "Yes",
            "type_of_cooling": "Static",
            "mobile": "Yes",
            "defrost": "Automatic",
            "max._ambient_temperature": 30,
            "brand": "COMBISTEEL",
            "refrigerant_quantity": 140,
            "energy_label": "B",
            "eprel_id": 2523652,
            "plug_and_play": "Yes"
        },
        "downloads": [
            {
                "label": "Manual 7472 Series ice cream displays",
                "url": "https://www.combisteel.com/en/amfile/file/download/file/1230999/product/1333/"
            },
            {
                "label": "Exploded view 7472.0115",
                "url": "https://www.combisteel.com/en/amfile/file/download/file/1231000/product/1333/"
            },
            {
                "label": "7472.0115 dimensions",
                "url": "https://www.combisteel.com/en/amfile/file/download/file/1231001/product/1333/"
            },
            {
                "label": "7472.0115 Energy Label",
                "url": "https://www.combisteel.com/en/amfile/file/download/file/1231002/product/1333/"
            }
        ],
        "accessories": [
            {
                "code": "7476.0225",
                "name": "ICE CREAM TRAY SS 5LTR",
                "url": "https://www.combisteel.com/en/7476-0225-ice-cream-tray-ss-5ltr.html",
                "image": "https://www.combisteel.com/media/catalog/product/cache/885770f149f21cca5edd4b51c2ad35e1/7/4/7476_0225-6514.jpg",
                "image_large": "https://www.combisteel.com/media/catalog/product/cache/885770f149f21cca5edd4b51c2ad35e1/7/4/7476_0225-6514.jpg",
                "price": 600,
                "price_currency": "CZK",
                "price_text": "600 Kč"
            },
            {
                "code": "7455.2020",
                "name": "ICE CREAM TRAY SS 5LTR",
                "url": "https://www.combisteel.com/en/7455-2020-ice-cream-tray-ss-5ltr.html",
                "image": "https://www.combisteel.com/static/version20251021072834/frontend/H1/combisteel/en_GB/Magento_Catalog/images/product/placeholder/small_image.jpg",
                "image_large": "https://www.combisteel.com/static/version20251021072834/frontend/H1/combisteel/en_GB/Magento_Catalog/images/product/placeholder/small_image.jpg",
                "price": 650,
                "price_currency": "CZK",
                "price_text": "650 Kč"
            }
        ]
    },
    {
        "code": "7472.0145",
        "name": "ICE CREAM DISPLAY CUBA 13X5 LTR",
        "url": "https://www.combisteel.com/en/7472-0145-ice-cream-display-cuba-13x5-ltr.html",
        "image": "https://www.combisteel.com/media/catalog/product/cache/885770f149f21cca5edd4b51c2ad35e1/7/4/7472_0145-10682.jpg",
        "image_large": "https://www.combisteel.com/media/catalog/product/cache/885770f149f21cca5edd4b51c2ad35e1/7/4/7472_0145-10682.jpg",
        "price": 78500,
        "price_currency": "CZK",
        "price_text": "78 500 Kč",
        "specs": {
            "ean_code": 7435137924968,
            "width": 1664,
            "depth": 842,
            "height": 1285,
            "gross_weight": 150,
            "voltage": 230,
            "frequency": 50,
            "electrical_power": 0.19,
            "cooling_agent": "R 290",
            "temperature_range": "-24/-14",
            "gross_capacity": 540,
            "dim._interior_wxdxh": "1530x560x688",
            "lights": "Yes",
            "type_of_cooling": "Static",
            "mobile": "Yes",
            "defrost": "Automatic",
            "max._ambient_temperature": 30,
            "brand": "COMBISTEEL",
            "energy_label": "B",
            "eprel_id": 2523736,
            "plug_and_play": "Yes"
        },
        "downloads": [
            {
                "label": "Manual 7472 Series ice cream displays",
                "url": "https://www.combisteel.com/en/amfile/file/download/file/1221459/product/1339/"
            },
            {
                "label": "Exploded view 7472.0140-0145 (2019)",
                "url": "https://www.combisteel.com/en/amfile/file/download/file/1221460/product/1339/"
            },
            {
                "label": "7472.0145 dimensions",
                "url": "https://www.combisteel.com/en/amfile/file/download/file/1221461/product/1339/"
            },
            {
                "label": "7472.0145 Energy Label",
                "url": "https://www.combisteel.com/en/amfile/file/download/file/1221462/product/1339/"
            }
        ],
        "accessories": [
            {
                "code": "7476.0225",
                "name": "ICE CREAM TRAY SS 5LTR",
                "url": "https://www.combisteel.com/en/7476-0225-ice-cream-tray-ss-5ltr.html",
                "image": "https://www.combisteel.com/media/catalog/product/cache/885770f149f21cca5edd4b51c2ad35e1/7/4/7476_0225-6514.jpg",
                "image_large": "https://www.combisteel.com/media/catalog/product/cache/885770f149f21cca5edd4b51c2ad35e1/7/4/7476_0225-6514.jpg",
                "price": 600,
                "price_currency": "CZK",
                "price_text": "600 Kč"
            },
            {
                "code": "7455.2020",
                "name": "ICE CREAM TRAY SS 5LTR",
                "url": "https://www.combisteel.com/en/7455-2020-ice-cream-tray-ss-5ltr.html",
                "image": "https://www.combisteel.com/static/version20251021072834/frontend/H1/combisteel/en_GB/Magento_Catalog/images/product/placeholder/small_image.jpg",
                "image_large": "https://www.combisteel.com/static/version20251021072834/frontend/H1/combisteel/en_GB/Magento_Catalog/images/product/placeholder/small_image.jpg",
                "price": 650,
                "price_currency": "CZK",
                "price_text": "650 Kč"
            }
        ]
    },
    {
        "code": "7472.0140",
        "name": "ICE CREAM DISPLAY IBIZA 8X5 LTR",
        "url": "https://www.combisteel.com/en/7472-0140-ice-cream-display-ibiza-8x5-ltr.html",
        "image": "https://www.combisteel.com/media/catalog/product/cache/885770f149f21cca5edd4b51c2ad35e1/7/4/7472_0140-10682.jpg",
        "image_large": "https://www.combisteel.com/media/catalog/product/cache/885770f149f21cca5edd4b51c2ad35e1/7/4/7472_0140-10682.jpg",
        "price": 66500,
        "price_currency": "CZK",
        "price_text": "66 500 Kč",
        "specs": {
            "ean_code": 7435137862833,
            "width": 1194,
            "depth": 842,
            "height": 1285,
            "gross_weight": 130,
            "voltage": 230,
            "frequency": 50,
            "electrical_power": 0.15,
            "cooling_agent": "R 290",
            "temperature_range": "-24/-14",
            "gross_capacity": 358,
            "dim._interior_wxdxh": "1060x560x688",
            "lights": "Yes",
            "type_of_cooling": "Static",
            "mobile": "Yes",
            "defrost": "Automatic",
            "max._ambient_temperature": 30,
            "brand": "COMBISTEEL",
            "refrigerant_quantity": 95,
            "energy_label": "B",
            "eprel_id": 2523704,
            "plug_and_play": "Yes"
        },
        "downloads": [
            {
                "label": "Manual 7472 Series ice cream displays",
                "url": "https://www.combisteel.com/en/amfile/file/download/file/1219750/product/1338/"
            },
            {
                "label": "Exploded view 7472.0140-0145 (2019)",
                "url": "https://www.combisteel.com/en/amfile/file/download/file/1219751/product/1338/"
            },
            {
                "label": "7472.0140 dimensions",
                "url": "https://www.combisteel.com/en/amfile/file/download/file/1219752/product/1338/"
            },
            {
                "label": "7472.0140 Energy Label",
                "url": "https://www.combisteel.com/en/amfile/file/download/file/1219753/product/1338/"
            }
        ],
        "accessories": [
            {
                "code": "7476.0225",
                "name": "ICE CREAM TRAY SS 5LTR",
                "url": "https://www.combisteel.com/en/7476-0225-ice-cream-tray-ss-5ltr.html",
                "image": "https://www.combisteel.com/media/catalog/product/cache/885770f149f21cca5edd4b51c2ad35e1/7/4/7476_0225-6514.jpg",
                "image_large": "https://www.combisteel.com/media/catalog/product/cache/885770f149f21cca5edd4b51c2ad35e1/7/4/7476_0225-6514.jpg",
                "price": 600,
                "price_currency": "CZK",
                "price_text": "600 Kč"
            },
            {
                "code": "7455.2020",
                "name": "ICE CREAM TRAY SS 5LTR",
                "url": "https://www.combisteel.com/en/7455-2020-ice-cream-tray-ss-5ltr.html",
                "image": "https://www.combisteel.com/static/version20251021072834/frontend/H1/combisteel/en_GB/Magento_Catalog/images/product/placeholder/small_image.jpg",
                "image_large": "https://www.combisteel.com/static/version20251021072834/frontend/H1/combisteel/en_GB/Magento_Catalog/images/product/placeholder/small_image.jpg",
                "price": 650,
                "price_currency": "CZK",
                "price_text": "650 Kč"
            }
        ]
    },
    {
        "code": "7472.0110",
        "name": "ICE CREAM DISPLAY MALTA 13X 5LTR",
        "url": "https://www.combisteel.com/en/7472-0110-ice-cream-display-malta-13x-5ltr.html",
        "image": "https://www.combisteel.com/media/catalog/product/cache/885770f149f21cca5edd4b51c2ad35e1/7/4/7472_0110-14290.jpg",
        "image_large": "https://www.combisteel.com/media/catalog/product/cache/885770f149f21cca5edd4b51c2ad35e1/7/4/7472_0110-14290.jpg",
        "price": 63500,
        "price_currency": "CZK",
        "price_text": "63 500 Kč",
        "specs": {
            "ean_code": 7435137797777,
            "width": 1662,
            "depth": 825,
            "height": 1257,
            "color": "White",
            "gross_weight": 130,
            "voltage": 230,
            "frequency": 50,
            "electrical_power": 0.63,
            "cooling_agent": "R 290",
            "capacity_in_units_per_time": "13x5 ltr",
            "temperature_range": "-22/-15",
            "gross_capacity": 557,
            "dim._interior_wxdxh": "1530x560x687",
            "lights": "Yes",
            "type_of_cooling": "Static",
            "mobile": "Yes",
            "defrost": "Manual",
            "max._ambient_temperature": 30,
            "brand": "COMBISTEEL",
            "refrigerant_quantity": "125 / 150",
            "energy_label": "A",
            "eprel_id": 2523645,
            "plug_and_play": "Yes"
        },
        "downloads": [
            {
                "label": "Manual 7472 Series ice cream displays",
                "url": "https://www.combisteel.com/en/amfile/file/download/file/1219410/product/1330/"
            },
            {
                "label": "Assembly glass cover 7472.0100-0105-0110",
                "url": "https://www.combisteel.com/en/amfile/file/download/file/1219411/product/1330/"
            },
            {
                "label": "Exploded view 7472.0110",
                "url": "https://www.combisteel.com/en/amfile/file/download/file/1219412/product/1330/"
            },
            {
                "label": "Exploded view 7472.0110 (2022)",
                "url": "https://www.combisteel.com/en/amfile/file/download/file/1219413/product/1330/"
            },
            {
                "label": "EU DECLARATION OF CONFORMITY 7472.0100-0105-0110",
                "url": "https://www.combisteel.com/en/amfile/file/download/file/1219414/product/1330/"
            },
            {
                "label": "7472.0110 dimensions",
                "url": "https://www.combisteel.com/en/amfile/file/download/file/1219415/product/1330/"
            },
            {
                "label": "7472.0110 Energy Label",
                "url": "https://www.combisteel.com/en/amfile/file/download/file/1219416/product/1330/"
            }
        ],
        "accessories": [
            {
                "code": "7472.0137",
                "name": "MOUNTING SET 0100- 0105 - 0110",
                "url": "https://www.combisteel.com/en/7472-0137-mounting-set-0100-0105-0110.html",
                "image": "https://www.combisteel.com/static/version20251021072834/frontend/H1/combisteel/en_GB/Magento_Catalog/images/product/placeholder/small_image.jpg",
                "image_large": "https://www.combisteel.com/static/version20251021072834/frontend/H1/combisteel/en_GB/Magento_Catalog/images/product/placeholder/small_image.jpg",
                "price": 2625,
                "price_currency": "CZK",
                "price_text": "2 625 Kč"
            },
            {
                "code": "7476.0225",
                "name": "ICE CREAM TRAY SS 5LTR",
                "url": "https://www.combisteel.com/en/7476-0225-ice-cream-tray-ss-5ltr.html",
                "image": "https://www.combisteel.com/media/catalog/product/cache/885770f149f21cca5edd4b51c2ad35e1/7/4/7476_0225-6514.jpg",
                "image_large": "https://www.combisteel.com/media/catalog/product/cache/885770f149f21cca5edd4b51c2ad35e1/7/4/7476_0225-6514.jpg",
                "price": 600,
                "price_currency": "CZK",
                "price_text": "600 Kč"
            },
            {
                "code": "7455.2020",
                "name": "ICE CREAM TRAY SS 5LTR",
                "url": "https://www.combisteel.com/en/7455-2020-ice-cream-tray-ss-5ltr.html",
                "image": "https://www.combisteel.com/static/version20251021072834/frontend/H1/combisteel/en_GB/Magento_Catalog/images/product/placeholder/small_image.jpg",
                "image_large": "https://www.combisteel.com/static/version20251021072834/frontend/H1/combisteel/en_GB/Magento_Catalog/images/product/placeholder/small_image.jpg",
                "price": 650,
                "price_currency": "CZK",
                "price_text": "650 Kč"
            }
        ]
    },
    {
        "code": "7472.0105",
        "name": "ICE CREAM DISPLAY CURACAO 10X5 LTR",
        "url": "https://www.combisteel.com/en/7472-0105-ice-cream-display-curacao-10x5-ltr.html",
        "image": "https://www.combisteel.com/media/catalog/product/cache/885770f149f21cca5edd4b51c2ad35e1/7/4/7472_0105-14290.jpg",
        "image_large": "https://www.combisteel.com/media/catalog/product/cache/885770f149f21cca5edd4b51c2ad35e1/7/4/7472_0105-14290.jpg",
        "price": 59000,
        "price_currency": "CZK",
        "price_text": "59 000 Kč",
        "specs": {
            "ean_code": 7435137797760,
            "width": 1447,
            "depth": 825,
            "height": 1257,
            "color": "White",
            "gross_weight": 116,
            "voltage": 230,
            "frequency": 50,
            "electrical_power": 0.5,
            "cooling_agent": "R 290",
            "capacity_in_units_per_time": "10x5 ltr",
            "temperature_range": "-22/-15",
            "gross_capacity": 454,
            "dim._interior_wxdxh": "1315x560x687",
            "lights": "Yes",
            "type_of_cooling": "Static",
            "mobile": "Yes",
            "defrost": "Manual",
            "max._ambient_temperature": 30,
            "brand": "COMBISTEEL",
            "refrigerant_quantity": 120,
            "energy_label": "A",
            "eprel_id": 2523624,
            "plug_and_play": "Yes"
        },
        "downloads": [
            {
                "label": "Manual 7472 Series ice cream displays",
                "url": "https://www.combisteel.com/en/amfile/file/download/file/1219633/product/1329/"
            },
            {
                "label": "Assembly glass cover 7472.0100-0105-0110",
                "url": "https://www.combisteel.com/en/amfile/file/download/file/1219634/product/1329/"
            },
            {
                "label": "Exploded view 7472.0105",
                "url": "https://www.combisteel.com/en/amfile/file/download/file/1219635/product/1329/"
            },
            {
                "label": "Exploded view 7472.0105 (2022)",
                "url": "https://www.combisteel.com/en/amfile/file/download/file/1219636/product/1329/"
            },
            {
                "label": "EU DECLARATION OF CONFORMITY 7472.0100-0105-0110",
                "url": "https://www.combisteel.com/en/amfile/file/download/file/1219637/product/1329/"
            },
            {
                "label": "7472.0105 dimensions",
                "url": "https://www.combisteel.com/en/amfile/file/download/file/1219638/product/1329/"
            },
            {
                "label": "7472.0105 Energy Label",
                "url": "https://www.combisteel.com/en/amfile/file/download/file/1219639/product/1329/"
            }
        ],
        "accessories": [
            {
                "code": "7472.0137",
                "name": "MOUNTING SET 0100- 0105 - 0110",
                "url": "https://www.combisteel.com/en/7472-0137-mounting-set-0100-0105-0110.html",
                "image": "https://www.combisteel.com/static/version20251021072834/frontend/H1/combisteel/en_GB/Magento_Catalog/images/product/placeholder/small_image.jpg",
                "image_large": "https://www.combisteel.com/static/version20251021072834/frontend/H1/combisteel/en_GB/Magento_Catalog/images/product/placeholder/small_image.jpg",
                "price": 2625,
                "price_currency": "CZK",
                "price_text": "2 625 Kč"
            },
            {
                "code": "7476.0225",
                "name": "ICE CREAM TRAY SS 5LTR",
                "url": "https://www.combisteel.com/en/7476-0225-ice-cream-tray-ss-5ltr.html",
                "image": "https://www.combisteel.com/media/catalog/product/cache/885770f149f21cca5edd4b51c2ad35e1/7/4/7476_0225-6514.jpg",
                "image_large": "https://www.combisteel.com/media/catalog/product/cache/885770f149f21cca5edd4b51c2ad35e1/7/4/7476_0225-6514.jpg",
                "price": 600,
                "price_currency": "CZK",
                "price_text": "600 Kč"
            },
            {
                "code": "7455.2020",
                "name": "ICE CREAM TRAY SS 5LTR",
                "url": "https://www.combisteel.com/en/7455-2020-ice-cream-tray-ss-5ltr.html",
                "image": "https://www.combisteel.com/static/version20251021072834/frontend/H1/combisteel/en_GB/Magento_Catalog/images/product/placeholder/small_image.jpg",
                "image_large": "https://www.combisteel.com/static/version20251021072834/frontend/H1/combisteel/en_GB/Magento_Catalog/images/product/placeholder/small_image.jpg",
                "price": 650,
                "price_currency": "CZK",
                "price_text": "650 Kč"
            }
        ]
    },
    {
        "code": "7472.0100",
        "name": "ICE CREAM DISPLAY BALI 9X5 LTR",
        "url": "https://www.combisteel.com/en/7472-0100-ice-cream-display-bali-9x5-ltr.html",
        "image": "https://www.combisteel.com/media/catalog/product/cache/885770f149f21cca5edd4b51c2ad35e1/7/4/7472_0100-14290.jpg",
        "image_large": "https://www.combisteel.com/media/catalog/product/cache/885770f149f21cca5edd4b51c2ad35e1/7/4/7472_0100-14290.jpg",
        "price": 53500,
        "price_currency": "CZK",
        "price_text": "53 500 Kč",
        "specs": {
            "ean_code": 7435137797753,
            "width": 1192,
            "depth": 825,
            "height": 1257,
            "color": "White",
            "gross_weight": 99,
            "voltage": 230,
            "frequency": 50,
            "electrical_power": 0.37,
            "model_tabletop/_freestanding/drop-in": "Freestanding",
            "cooling_agent": "R 290",
            "capacity_in_units_per_time": "9x5 ltr",
            "temperature_range": "-22/-15",
            "gross_capacity": 354,
            "dim._interior_wxdxh": "1060x560x687",
            "lights": "Yes",
            "type_of_cooling": "Static",
            "mobile": "Yes",
            "under_cooling": "Yes",
            "execution_window": "curved",
            "defrost": "Manual",
            "max._ambient_temperature": 30,
            "brand": "COMBISTEEL",
            "refrigerant_quantity": "135 / 150",
            "energy_label": "A",
            "eprel_id": 2516540,
            "plug_and_play": "Yes"
        },
        "downloads": [
            {
                "label": "Manual 7472 Series ice cream displays",
                "url": "https://www.combisteel.com/en/amfile/file/download/file/1229629/product/1328/"
            },
            {
                "label": "Assembly glass cover 7472.0100-0105-0110",
                "url": "https://www.combisteel.com/en/amfile/file/download/file/1229630/product/1328/"
            },
            {
                "label": "Exploded view 7472.0100",
                "url": "https://www.combisteel.com/en/amfile/file/download/file/1229631/product/1328/"
            },
            {
                "label": "Exploded view 7472.0100 (2022)",
                "url": "https://www.combisteel.com/en/amfile/file/download/file/1229632/product/1328/"
            },
            {
                "label": "EU DECLARATION OF CONFORMITY 7472.0100-0105-0110",
                "url": "https://www.combisteel.com/en/amfile/file/download/file/1229633/product/1328/"
            },
            {
                "label": "7472.0100 dimensions",
                "url": "https://www.combisteel.com/en/amfile/file/download/file/1229634/product/1328/"
            },
            {
                "label": "7472.0100 Energy Label",
                "url": "https://www.combisteel.com/en/amfile/file/download/file/1229635/product/1328/"
            }
        ],
        "accessories": [
            {
                "code": "7472.0137",
                "name": "MOUNTING SET 0100- 0105 - 0110",
                "url": "https://www.combisteel.com/en/7472-0137-mounting-set-0100-0105-0110.html",
                "image": "https://www.combisteel.com/static/version20251021072834/frontend/H1/combisteel/en_GB/Magento_Catalog/images/product/placeholder/small_image.jpg",
                "image_large": "https://www.combisteel.com/static/version20251021072834/frontend/H1/combisteel/en_GB/Magento_Catalog/images/product/placeholder/small_image.jpg",
                "price": 2625,
                "price_currency": "CZK",
                "price_text": "2 625 Kč"
            },
            {
                "code": "7476.0225",
                "name": "ICE CREAM TRAY SS 5LTR",
                "url": "https://www.combisteel.com/en/7476-0225-ice-cream-tray-ss-5ltr.html",
                "image": "https://www.combisteel.com/media/catalog/product/cache/885770f149f21cca5edd4b51c2ad35e1/7/4/7476_0225-6514.jpg",
                "image_large": "https://www.combisteel.com/media/catalog/product/cache/885770f149f21cca5edd4b51c2ad35e1/7/4/7476_0225-6514.jpg",
                "price": 600,
                "price_currency": "CZK",
                "price_text": "600 Kč"
            },
            {
                "code": "7455.2020",
                "name": "ICE CREAM TRAY SS 5LTR",
                "url": "https://www.combisteel.com/en/7455-2020-ice-cream-tray-ss-5ltr.html",
                "image": "https://www.combisteel.com/static/version20251021072834/frontend/H1/combisteel/en_GB/Magento_Catalog/images/product/placeholder/small_image.jpg",
                "image_large": "https://www.combisteel.com/static/version20251021072834/frontend/H1/combisteel/en_GB/Magento_Catalog/images/product/placeholder/small_image.jpg",
                "price": 650,
                "price_currency": "CZK",
                "price_text": "650 Kč"
            }
        ]
    },
    {
        "code": "7472.0134",
        "name": "ICE CREAM DISPLAY TENERIFE BLACK 10X5 LTR",
        "url": "https://www.combisteel.com/en/7472-0134-ice-cream-display-tenerife-black-10x5-ltr.html",
        "image": "https://www.combisteel.com/media/catalog/product/cache/885770f149f21cca5edd4b51c2ad35e1/7/4/7472_0134.jpg",
        "image_large": "https://www.combisteel.com/media/catalog/product/cache/885770f149f21cca5edd4b51c2ad35e1/7/4/7472_0134.jpg",
        "price": 39750,
        "price_currency": "CZK",
        "price_text": "39 750 Kč",
        "specs": {
            "ean_code": 7422242973929,
            "width": 1439,
            "depth": 727,
            "height": 1229,
            "color": "Black",
            "gross_weight": 101,
            "particulars": "Storage space for 10 ice bins of 5L (36x16.5)",
            "voltage": 230,
            "frequency": 50,
            "electrical_power": 0.26,
            "cooling_agent": "R 290",
            "capacity_in_units_per_time": "10x5 ltr",
            "temperature_range": "-24/-14",
            "gross_capacity": 454,
            "dim._interior_wxdxh": "1315x560x688",
            "lights": "No",
            "type_of_cooling": "Static",
            "mobile": "Yes",
            "noise_level": 50,
            "under_cooling": "Yes",
            "defrost": "Manual",
            "max._ambient_temperature": 30,
            "power_consumption": 3.64,
            "brand": "COMBISTEEL",
            "refrigerant_quantity": 120,
            "energy_label": "A",
            "eprel_id": 1941430,
            "plug_and_play": "Yes"
        },
        "downloads": [
            {
                "label": "Energy label 7472.0134",
                "url": "https://www.combisteel.com/en/amfile/file/download/file/1217226/product/4674/"
            },
            {
                "label": "Manual 7472 Series ice cream displays",
                "url": "https://www.combisteel.com/en/amfile/file/download/file/1217227/product/4674/"
            },
            {
                "label": "Assembly Glass Cover 7472.0124-0125-0129-0130-0134-0135",
                "url": "https://www.combisteel.com/en/amfile/file/download/file/1217228/product/4674/"
            },
            {
                "label": "EU DECLARATION OF CONFORMITY 7472.0124-0125-0129-0130-0134-0135",
                "url": "https://www.combisteel.com/en/amfile/file/download/file/1217229/product/4674/"
            },
            {
                "label": "7472.0134-0135 dimensions",
                "url": "https://www.combisteel.com/en/amfile/file/download/file/1217230/product/4674/"
            },
            {
                "label": "Exploded view 7472.0134 (2025)",
                "url": "https://www.combisteel.com/en/amfile/file/download/file/1217231/product/4674/"
            }
        ],
        "accessories": [
            {
                "code": "7476.0225",
                "name": "ICE CREAM TRAY SS 5LTR",
                "url": "https://www.combisteel.com/en/7476-0225-ice-cream-tray-ss-5ltr.html",
                "image": "https://www.combisteel.com/media/catalog/product/cache/885770f149f21cca5edd4b51c2ad35e1/7/4/7476_0225-6514.jpg",
                "image_large": "https://www.combisteel.com/media/catalog/product/cache/885770f149f21cca5edd4b51c2ad35e1/7/4/7476_0225-6514.jpg",
                "price": 600,
                "price_currency": "CZK",
                "price_text": "600 Kč"
            },
            {
                "code": "7472.0138",
                "name": "MOUNTING SET 0124-0125-0129-0130-0134-0135",
                "url": "https://www.combisteel.com/en/7472-0138-mounting-set-0124-0125-0129-0130-0134-0135.html",
                "image": "https://www.combisteel.com/static/version20251021072834/frontend/H1/combisteel/en_GB/Magento_Catalog/images/product/placeholder/small_image.jpg",
                "image_large": "https://www.combisteel.com/static/version20251021072834/frontend/H1/combisteel/en_GB/Magento_Catalog/images/product/placeholder/small_image.jpg",
                "price": 3375,
                "price_currency": "CZK",
                "price_text": "3 375 Kč"
            },
            {
                "code": "7455.2020",
                "name": "ICE CREAM TRAY SS 5LTR",
                "url": "https://www.combisteel.com/en/7455-2020-ice-cream-tray-ss-5ltr.html",
                "image": "https://www.combisteel.com/static/version20251021072834/frontend/H1/combisteel/en_GB/Magento_Catalog/images/product/placeholder/small_image.jpg",
                "image_large": "https://www.combisteel.com/static/version20251021072834/frontend/H1/combisteel/en_GB/Magento_Catalog/images/product/placeholder/small_image.jpg",
                "price": 650,
                "price_currency": "CZK",
                "price_text": "650 Kč"
            }
        ]
    },
    {
        "code": "7472.0135",
        "name": "ICE CREAM DISPLAY TENERIFE 10X5 LTR",
        "url": "https://www.combisteel.com/en/7472-0135-ice-cream-display-tenerife-10x5-ltr.html",
        "image": "https://www.combisteel.com/media/catalog/product/cache/885770f149f21cca5edd4b51c2ad35e1/7/4/7472_0135-2_3.jpg",
        "image_large": "https://www.combisteel.com/media/catalog/product/cache/885770f149f21cca5edd4b51c2ad35e1/7/4/7472_0135-2_3.jpg",
        "price": 39375,
        "price_currency": "CZK",
        "price_text": "39 375 Kč",
        "specs": {
            "ean_code": 7435137798705,
            "width": 1439,
            "depth": 727,
            "height": 1229,
            "color": "White",
            "gross_weight": 101,
            "particulars": "De opslagruimte is voor 10 ijsbakken van 5L. (36x16,5)",
            "voltage": 230,
            "frequency": 50,
            "electrical_power": 0.26,
            "cooling_agent": "R 290",
            "capacity_in_units_per_time": "10x5 ltr",
            "temperature_range": "-24/-14",
            "gross_capacity": 454,
            "dim._interior_wxdxh": "1315x560x688",
            "lights": "No",
            "type_of_cooling": "Static",
            "mobile": "Yes",
            "noise_level": 50,
            "under_cooling": "Yes",
            "defrost": "Manual",
            "max._ambient_temperature": 30,
            "power_consumption": 3.64,
            "brand": "COMBISTEEL",
            "refrigerant_quantity": 120,
            "energy_label": "A",
            "eprel_id": 1941440,
            "plug_and_play": "Yes"
        },
        "downloads": [
            {
                "label": "Energy label 7472.0135",
                "url": "https://www.combisteel.com/en/amfile/file/download/file/1227335/product/1337/"
            },
            {
                "label": "Manual 7472 Series ice cream displays",
                "url": "https://www.combisteel.com/en/amfile/file/download/file/1227336/product/1337/"
            },
            {
                "label": "Assembly Glass Cover 7472.0124-0125-0129-0130-0134-0135",
                "url": "https://www.combisteel.com/en/amfile/file/download/file/1227337/product/1337/"
            },
            {
                "label": "Exploded view 7472.0125-0130-0135 (2020)",
                "url": "https://www.combisteel.com/en/amfile/file/download/file/1227338/product/1337/"
            },
            {
                "label": "EU DECLARATION OF CONFORMITY 7472.0124-0125-0129-0130-0134-0135",
                "url": "https://www.combisteel.com/en/amfile/file/download/file/1227339/product/1337/"
            },
            {
                "label": "7472.0134-0135 dimensions",
                "url": "https://www.combisteel.com/en/amfile/file/download/file/1227340/product/1337/"
            }
        ],
        "accessories": [
            {
                "code": "7472.0138",
                "name": "MOUNTING SET 0124-0125-0129-0130-0134-0135",
                "url": "https://www.combisteel.com/en/7472-0138-mounting-set-0124-0125-0129-0130-0134-0135.html",
                "image": "https://www.combisteel.com/static/version20251021072834/frontend/H1/combisteel/en_GB/Magento_Catalog/images/product/placeholder/small_image.jpg",
                "image_large": "https://www.combisteel.com/static/version20251021072834/frontend/H1/combisteel/en_GB/Magento_Catalog/images/product/placeholder/small_image.jpg",
                "price": 3375,
                "price_currency": "CZK",
                "price_text": "3 375 Kč"
            },
            {
                "code": "7476.0225",
                "name": "ICE CREAM TRAY SS 5LTR",
                "url": "https://www.combisteel.com/en/7476-0225-ice-cream-tray-ss-5ltr.html",
                "image": "https://www.combisteel.com/media/catalog/product/cache/885770f149f21cca5edd4b51c2ad35e1/7/4/7476_0225-6514.jpg",
                "image_large": "https://www.combisteel.com/media/catalog/product/cache/885770f149f21cca5edd4b51c2ad35e1/7/4/7476_0225-6514.jpg",
                "price": 600,
                "price_currency": "CZK",
                "price_text": "600 Kč"
            },
            {
                "code": "7455.2020",
                "name": "ICE CREAM TRAY SS 5LTR",
                "url": "https://www.combisteel.com/en/7455-2020-ice-cream-tray-ss-5ltr.html",
                "image": "https://www.combisteel.com/static/version20251021072834/frontend/H1/combisteel/en_GB/Magento_Catalog/images/product/placeholder/small_image.jpg",
                "image_large": "https://www.combisteel.com/static/version20251021072834/frontend/H1/combisteel/en_GB/Magento_Catalog/images/product/placeholder/small_image.jpg",
                "price": 650,
                "price_currency": "CZK",
                "price_text": "650 Kč"
            }
        ]
    },
    {
        "code": "7472.0129",
        "name": "ICE CREAM DISPLAY JAVA BLACK 8x5 LTR",
        "url": "https://www.combisteel.com/en/7472-0129-ice-cream-display-java-black-8x5-ltr.html",
        "image": "https://www.combisteel.com/media/catalog/product/cache/885770f149f21cca5edd4b51c2ad35e1/7/4/7472_0129_1.jpg",
        "image_large": "https://www.combisteel.com/media/catalog/product/cache/885770f149f21cca5edd4b51c2ad35e1/7/4/7472_0129_1.jpg",
        "price": 34875,
        "price_currency": "CZK",
        "price_text": "34 875 Kč",
        "specs": {
            "ean_code": 7422242973912,
            "width": 1184,
            "depth": 684,
            "height": 1229,
            "color": "Black",
            "gross_weight": 85,
            "particulars": "Storage space for 10 ice bins of 5L (36x16.5)",
            "voltage": 230,
            "frequency": 50,
            "electrical_power": 0.2,
            "cooling_agent": "R 290",
            "capacity_in_units_per_time": "8x5 ltr",
            "temperature_range": "-24/-14",
            "gross_capacity": 355,
            "dim._interior_wxdxh": "1060x560x688",
            "lights": "No",
            "type_of_cooling": "Static",
            "mobile": "Yes",
            "noise_level": 50,
            "under_cooling": "Yes",
            "defrost": "Manual",
            "max._ambient_temperature": 30,
            "power_consumption": 3.01,
            "brand": "COMBISTEEL",
            "refrigerant_quantity": "110 / 150",
            "energy_label": "A",
            "eprel_id": 1941424,
            "plug_and_play": "Yes"
        },
        "downloads": [
            {
                "label": "Energy label 7472.0129",
                "url": "https://www.combisteel.com/en/amfile/file/download/file/1216214/product/4673/"
            },
            {
                "label": "Manual 7472 Series ice cream displays",
                "url": "https://www.combisteel.com/en/amfile/file/download/file/1216215/product/4673/"
            },
            {
                "label": "Assembly Glass Cover 7472.0124-0125-0129-0130-0134-0135",
                "url": "https://www.combisteel.com/en/amfile/file/download/file/1216216/product/4673/"
            },
            {
                "label": "EU DECLARATION OF CONFORMITY 7472.0124-0125-0129-0130-0134-0135",
                "url": "https://www.combisteel.com/en/amfile/file/download/file/1216217/product/4673/"
            },
            {
                "label": "7472.0129-0130 dimensions",
                "url": "https://www.combisteel.com/en/amfile/file/download/file/1216218/product/4673/"
            },
            {
                "label": "Exploded view 7472.0129 (2025)",
                "url": "https://www.combisteel.com/en/amfile/file/download/file/1216219/product/4673/"
            }
        ],
        "accessories": [
            {
                "code": "7476.0225",
                "name": "ICE CREAM TRAY SS 5LTR",
                "url": "https://www.combisteel.com/en/7476-0225-ice-cream-tray-ss-5ltr.html",
                "image": "https://www.combisteel.com/media/catalog/product/cache/885770f149f21cca5edd4b51c2ad35e1/7/4/7476_0225-6514.jpg",
                "image_large": "https://www.combisteel.com/media/catalog/product/cache/885770f149f21cca5edd4b51c2ad35e1/7/4/7476_0225-6514.jpg",
                "price": 600,
                "price_currency": "CZK",
                "price_text": "600 Kč"
            },
            {
                "code": "7472.0138",
                "name": "MOUNTING SET 0124-0125-0129-0130-0134-0135",
                "url": "https://www.combisteel.com/en/7472-0138-mounting-set-0124-0125-0129-0130-0134-0135.html",
                "image": "https://www.combisteel.com/static/version20251021072834/frontend/H1/combisteel/en_GB/Magento_Catalog/images/product/placeholder/small_image.jpg",
                "image_large": "https://www.combisteel.com/static/version20251021072834/frontend/H1/combisteel/en_GB/Magento_Catalog/images/product/placeholder/small_image.jpg",
                "price": 3375,
                "price_currency": "CZK",
                "price_text": "3 375 Kč"
            },
            {
                "code": "7455.2020",
                "name": "ICE CREAM TRAY SS 5LTR",
                "url": "https://www.combisteel.com/en/7455-2020-ice-cream-tray-ss-5ltr.html",
                "image": "https://www.combisteel.com/static/version20251021072834/frontend/H1/combisteel/en_GB/Magento_Catalog/images/product/placeholder/small_image.jpg",
                "image_large": "https://www.combisteel.com/static/version20251021072834/frontend/H1/combisteel/en_GB/Magento_Catalog/images/product/placeholder/small_image.jpg",
                "price": 650,
                "price_currency": "CZK",
                "price_text": "650 Kč"
            }
        ]
    },
    {
        "code": "7292.0005",
        "name": "COUNTERTOP MODEL ICE CREAM DISPLAY WHITE\nOPENS ON THE OPERATING SIDE",
        "url": "https://www.combisteel.com/en/catalog/product/view/id/3649/s/7292-0005-countertop-model-ice-cream-display-white-opens-on-the-operating-side/category/525/",
        "image": "https://www.combisteel.com/media/catalog/product/cache/885770f149f21cca5edd4b51c2ad35e1/7/2/7292_0005-13231.jpg",
        "image_large": "https://www.combisteel.com/media/catalog/product/cache/885770f149f21cca5edd4b51c2ad35e1/7/2/7292_0005-13231.jpg",
        "price": 34375,
        "price_currency": "CZK",
        "price_text": "34 375 Kč",
        "specs": {
            "ean_code": 7422242913956,
            "width": 670,
            "depth": 750,
            "height": 375,
            "color": "White",
            "gross_weight": 67,
            "particulars": "Exclusief ijsbakken",
            "voltage": 230,
            "frequency": 50,
            "electrical_power": 195,
            "cooling_agent": "R 290",
            "capacity_in_units_per_time": "3x5 ltr",
            "temperature_range": "-16/-18",
            "dim._interior_wxdxh": "550x415x150",
            "lights": "Yes",
            "type_of_cooling": "Static",
            "lockable": "No",
            "defrost": "Manual",
            "max._ambient_temperature": 30,
            "brand": "COMBISTEEL",
            "refrigerant_quantity": 50,
            "energy_label": "B",
            "eprel_id": 2052295,
            "plug_and_play": "Yes"
        },
        "downloads": [
            {
                "label": "Exploded view 7292.0005-0010-0015-0020",
                "url": "https://www.combisteel.com/en/amfile/file/download/file/1212487/product/3649/"
            },
            {
                "label": "Manual 7292 series",
                "url": "https://www.combisteel.com/en/amfile/file/download/file/1212488/product/3649/"
            },
            {
                "label": "EU DECLARATION OF CONFORMITY 7292.0005-0010-0015-0020",
                "url": "https://www.combisteel.com/en/amfile/file/download/file/1212489/product/3649/"
            },
            {
                "label": "7292.0005 dimensions",
                "url": "https://www.combisteel.com/en/amfile/file/download/file/1212490/product/3649/"
            },
            {
                "label": "7292.0005 Energy Label 1",
                "url": "https://www.combisteel.com/en/amfile/file/download/file/1212491/product/3649/"
            }
        ],
        "accessories": [
            {
                "code": "7476.0225",
                "name": "ICE CREAM TRAY SS 5LTR",
                "url": "https://www.combisteel.com/en/7476-0225-ice-cream-tray-ss-5ltr.html",
                "image": "https://www.combisteel.com/media/catalog/product/cache/885770f149f21cca5edd4b51c2ad35e1/7/4/7476_0225-6514.jpg",
                "image_large": "https://www.combisteel.com/media/catalog/product/cache/885770f149f21cca5edd4b51c2ad35e1/7/4/7476_0225-6514.jpg",
                "price": 600,
                "price_currency": "CZK",
                "price_text": "600 Kč"
            },
            {
                "code": "7455.2020",
                "name": "ICE CREAM TRAY SS 5LTR",
                "url": "https://www.combisteel.com/en/7455-2020-ice-cream-tray-ss-5ltr.html",
                "image": "https://www.combisteel.com/static/version20251021072834/frontend/H1/combisteel/en_GB/Magento_Catalog/images/product/placeholder/small_image.jpg",
                "image_large": "https://www.combisteel.com/static/version20251021072834/frontend/H1/combisteel/en_GB/Magento_Catalog/images/product/placeholder/small_image.jpg",
                "price": 650,
                "price_currency": "CZK",
                "price_text": "650 Kč"
            }
        ]
    },
    {
        "code": "7292.0010",
        "name": "COUNTERTOP MODEL ICE CREAM DISPLAY BLACK\nOPENS ON THE OPERATING SIDE",
        "url": "https://www.combisteel.com/en/7292-0010-countertop-model-ice-cream-display-black-opens-on-the-operating-side.html",
        "image": "https://www.combisteel.com/media/catalog/product/cache/885770f149f21cca5edd4b51c2ad35e1/7/2/7292_0010-13236.jpg",
        "image_large": "https://www.combisteel.com/media/catalog/product/cache/885770f149f21cca5edd4b51c2ad35e1/7/2/7292_0010-13236.jpg",
        "price": 34375,
        "price_currency": "CZK",
        "price_text": "34 375 Kč",
        "specs": {
            "ean_code": 7422242913963,
            "width": 670,
            "depth": 750,
            "height": 375,
            "color": "Black",
            "gross_weight": 67,
            "particulars": "Exclusief ijsbakken",
            "voltage": 230,
            "frequency": 50,
            "electrical_power": 195,
            "cooling_agent": "R 290",
            "capacity_in_units_per_time": "3x5 ltr",
            "temperature_range": "-16/-18",
            "dim._interior_wxdxh": "550x415x150",
            "lights": "Yes",
            "type_of_cooling": "Static",
            "lockable": "No",
            "defrost": "Manual",
            "max._ambient_temperature": 30,
            "brand": "COMBISTEEL",
            "refrigerant_quantity": 50,
            "energy_label": "B",
            "eprel_id": 2052330,
            "plug_and_play": "Yes"
        },
        "downloads": [
            {
                "label": "Manual 7292 series",
                "url": "https://www.combisteel.com/en/amfile/file/download/file/1212492/product/3650/"
            },
            {
                "label": "Exploded view 7292.0005-0010-0015-0020",
                "url": "https://www.combisteel.com/en/amfile/file/download/file/1212493/product/3650/"
            },
            {
                "label": "EU DECLARATION OF CONFORMITY 7292.0005-0010-0015-0020",
                "url": "https://www.combisteel.com/en/amfile/file/download/file/1212494/product/3650/"
            },
            {
                "label": "7292.0010 dimensions",
                "url": "https://www.combisteel.com/en/amfile/file/download/file/1212495/product/3650/"
            },
            {
                "label": "7292.0010 Energy Label",
                "url": "https://www.combisteel.com/en/amfile/file/download/file/1212496/product/3650/"
            }
        ],
        "accessories": [
            {
                "code": "7476.0225",
                "name": "ICE CREAM TRAY SS 5LTR",
                "url": "https://www.combisteel.com/en/7476-0225-ice-cream-tray-ss-5ltr.html",
                "image": "https://www.combisteel.com/media/catalog/product/cache/885770f149f21cca5edd4b51c2ad35e1/7/4/7476_0225-6514.jpg",
                "image_large": "https://www.combisteel.com/media/catalog/product/cache/885770f149f21cca5edd4b51c2ad35e1/7/4/7476_0225-6514.jpg",
                "price": 600,
                "price_currency": "CZK",
                "price_text": "600 Kč"
            },
            {
                "code": "7455.2020",
                "name": "ICE CREAM TRAY SS 5LTR",
                "url": "https://www.combisteel.com/en/7455-2020-ice-cream-tray-ss-5ltr.html",
                "image": "https://www.combisteel.com/static/version20251021072834/frontend/H1/combisteel/en_GB/Magento_Catalog/images/product/placeholder/small_image.jpg",
                "image_large": "https://www.combisteel.com/static/version20251021072834/frontend/H1/combisteel/en_GB/Magento_Catalog/images/product/placeholder/small_image.jpg",
                "price": 650,
                "price_currency": "CZK",
                "price_text": "650 Kč"
            }
        ]
    },
    {
        "code": "7292.0015",
        "name": "COUNTERTOP MODEL ICE CREAM DISPLAY WHITE\nOPENS ON THE CUSTOMER SIDE",
        "url": "https://www.combisteel.com/en/catalog/product/view/id/3651/s/7292-0015-countertop-model-ice-cream-display-white-opens-on-the-customer-side/category/525/",
        "image": "https://www.combisteel.com/media/catalog/product/cache/885770f149f21cca5edd4b51c2ad35e1/7/2/7292_0015-15450.jpg",
        "image_large": "https://www.combisteel.com/media/catalog/product/cache/885770f149f21cca5edd4b51c2ad35e1/7/2/7292_0015-15450.jpg",
        "price": 34375,
        "price_currency": "CZK",
        "price_text": "34 375 Kč",
        "specs": {
            "ean_code": 7422242913987,
            "width": 670,
            "depth": 750,
            "height": 375,
            "color": "White",
            "gross_weight": 67,
            "particulars": "Exclusief ijsbakken",
            "voltage": 230,
            "frequency": 50,
            "electrical_power": 195,
            "cooling_agent": "R 290",
            "capacity_in_units_per_time": "3x5 ltr",
            "temperature_range": "-16/-18",
            "dim._interior_wxdxh": "550x415x150",
            "lights": "Yes",
            "type_of_cooling": "Static",
            "lockable": "No",
            "defrost": "Manual",
            "max._ambient_temperature": 30,
            "brand": "COMBISTEEL",
            "refrigerant_quantity": 50,
            "energy_label": "B",
            "eprel_id": 2052337,
            "plug_and_play": "Yes"
        },
        "downloads": [
            {
                "label": "Manual 7292 series",
                "url": "https://www.combisteel.com/en/amfile/file/download/file/1212497/product/3651/"
            },
            {
                "label": "Exploded view 7292.0005-0010-0015-0020",
                "url": "https://www.combisteel.com/en/amfile/file/download/file/1212498/product/3651/"
            },
            {
                "label": "EU DECLARATION OF CONFORMITY 7292.0005-0010-0015-0020",
                "url": "https://www.combisteel.com/en/amfile/file/download/file/1212499/product/3651/"
            },
            {
                "label": "7292.0015 dimensions",
                "url": "https://www.combisteel.com/en/amfile/file/download/file/1212500/product/3651/"
            },
            {
                "label": "7292.0015 Energy Label",
                "url": "https://www.combisteel.com/en/amfile/file/download/file/1212501/product/3651/"
            }
        ],
        "accessories": [
            {
                "code": "7476.0225",
                "name": "ICE CREAM TRAY SS 5LTR",
                "url": "https://www.combisteel.com/en/7476-0225-ice-cream-tray-ss-5ltr.html",
                "image": "https://www.combisteel.com/media/catalog/product/cache/885770f149f21cca5edd4b51c2ad35e1/7/4/7476_0225-6514.jpg",
                "image_large": "https://www.combisteel.com/media/catalog/product/cache/885770f149f21cca5edd4b51c2ad35e1/7/4/7476_0225-6514.jpg",
                "price": 600,
                "price_currency": "CZK",
                "price_text": "600 Kč"
            },
            {
                "code": "7455.2020",
                "name": "ICE CREAM TRAY SS 5LTR",
                "url": "https://www.combisteel.com/en/7455-2020-ice-cream-tray-ss-5ltr.html",
                "image": "https://www.combisteel.com/static/version20251021072834/frontend/H1/combisteel/en_GB/Magento_Catalog/images/product/placeholder/small_image.jpg",
                "image_large": "https://www.combisteel.com/static/version20251021072834/frontend/H1/combisteel/en_GB/Magento_Catalog/images/product/placeholder/small_image.jpg",
                "price": 650,
                "price_currency": "CZK",
                "price_text": "650 Kč"
            }
        ]
    },
    {
        "code": "7292.0020",
        "name": "COUNTERTOP MODEL ICE CREAM DISPLAY BLACK\nOPENS ON THE CUSTOMER SIDE",
        "url": "https://www.combisteel.com/en/7292-0020-countertop-model-ice-cream-display-black-opens-on-the-customer-side.html",
        "image": "https://www.combisteel.com/media/catalog/product/cache/885770f149f21cca5edd4b51c2ad35e1/7/2/7292_0020-13323.jpg",
        "image_large": "https://www.combisteel.com/media/catalog/product/cache/885770f149f21cca5edd4b51c2ad35e1/7/2/7292_0020-13323.jpg",
        "price": 34375,
        "price_currency": "CZK",
        "price_text": "34 375 Kč",
        "specs": {
            "ean_code": 7422242913994,
            "width": 670,
            "depth": 750,
            "height": 375,
            "color": "Black",
            "gross_weight": 67,
            "particulars": "Exclusief ijsbakken",
            "voltage": 230,
            "frequency": 50,
            "electrical_power": 195,
            "cooling_agent": "R 290",
            "capacity_in_units_per_time": "3x5 ltr",
            "temperature_range": "-16/-18",
            "dim._interior_wxdxh": "550x415x150",
            "lights": "Yes",
            "type_of_cooling": "Static",
            "lockable": "No",
            "defrost": "Manual",
            "max._ambient_temperature": 30,
            "brand": "COMBISTEEL",
            "refrigerant_quantity": 50,
            "energy_label": "B",
            "eprel_id": 2052344,
            "plug_and_play": "Yes"
        },
        "downloads": [
            {
                "label": "Manual 7292 series",
                "url": "https://www.combisteel.com/en/amfile/file/download/file/1212502/product/3652/"
            },
            {
                "label": "Exploded view 7292.0005-0010-0015-0020",
                "url": "https://www.combisteel.com/en/amfile/file/download/file/1212503/product/3652/"
            },
            {
                "label": "EU DECLARATION OF CONFORMITY 7292.0005-0010-0015-0020",
                "url": "https://www.combisteel.com/en/amfile/file/download/file/1212504/product/3652/"
            },
            {
                "label": "7292.0020 dimensions",
                "url": "https://www.combisteel.com/en/amfile/file/download/file/1212505/product/3652/"
            },
            {
                "label": "7292.0020 Energy Label",
                "url": "https://www.combisteel.com/en/amfile/file/download/file/1212506/product/3652/"
            }
        ],
        "accessories": [
            {
                "code": "7476.0225",
                "name": "ICE CREAM TRAY SS 5LTR",
                "url": "https://www.combisteel.com/en/7476-0225-ice-cream-tray-ss-5ltr.html",
                "image": "https://www.combisteel.com/media/catalog/product/cache/885770f149f21cca5edd4b51c2ad35e1/7/4/7476_0225-6514.jpg",
                "image_large": "https://www.combisteel.com/media/catalog/product/cache/885770f149f21cca5edd4b51c2ad35e1/7/4/7476_0225-6514.jpg",
                "price": 600,
                "price_currency": "CZK",
                "price_text": "600 Kč"
            },
            {
                "code": "7455.2020",
                "name": "ICE CREAM TRAY SS 5LTR",
                "url": "https://www.combisteel.com/en/7455-2020-ice-cream-tray-ss-5ltr.html",
                "image": "https://www.combisteel.com/static/version20251021072834/frontend/H1/combisteel/en_GB/Magento_Catalog/images/product/placeholder/small_image.jpg",
                "image_large": "https://www.combisteel.com/static/version20251021072834/frontend/H1/combisteel/en_GB/Magento_Catalog/images/product/placeholder/small_image.jpg",
                "price": 650,
                "price_currency": "CZK",
                "price_text": "650 Kč"
            }
        ]
    },
    {
        "code": "7472.0130",
        "name": "ICE CREAM DISPLAY JAVA 8x5 LTR",
        "url": "https://www.combisteel.com/en/7472-0130-ice-cream-display-java-8x5-ltr.html",
        "image": "https://www.combisteel.com/media/catalog/product/cache/885770f149f21cca5edd4b51c2ad35e1/7/4/7472_0135-2_1.jpg",
        "image_large": "https://www.combisteel.com/media/catalog/product/cache/885770f149f21cca5edd4b51c2ad35e1/7/4/7472_0135-2_1.jpg",
        "price": 34125,
        "price_currency": "CZK",
        "price_text": "34 125 Kč",
        "specs": {
            "ean_code": 7435137797791,
            "width": 1184,
            "depth": 727,
            "height": 1229,
            "color": "White",
            "gross_weight": 85,
            "particulars": "Storage space for 10 ice bins of 5L (36x16.5)",
            "voltage": 230,
            "frequency": 50,
            "electrical_power": 0.2,
            "cooling_agent": "R 290",
            "capacity_in_units_per_time": "8x5 ltr",
            "temperature_range": "-24/-14",
            "gross_capacity": 355,
            "dim._interior_wxdxh": "1060x560x688",
            "lights": "No",
            "type_of_cooling": "Static",
            "mobile": "Yes",
            "noise_level": 50,
            "under_cooling": "Yes",
            "defrost": "Manual",
            "max._ambient_temperature": 30,
            "power_consumption": 3.01,
            "brand": "COMBISTEEL",
            "refrigerant_quantity": "110 / 150",
            "energy_label": "A",
            "eprel_id": 1941429,
            "plug_and_play": "Yes"
        },
        "downloads": [
            {
                "label": "Energy label 7472.0130",
                "url": "https://www.combisteel.com/en/amfile/file/download/file/1236760/product/1336/"
            },
            {
                "label": "Manual 7472 Series ice cream displays",
                "url": "https://www.combisteel.com/en/amfile/file/download/file/1236761/product/1336/"
            },
            {
                "label": "Assembly Glass Cover 7472.0124-0125-0129-0130-0134-0135",
                "url": "https://www.combisteel.com/en/amfile/file/download/file/1236762/product/1336/"
            },
            {
                "label": "Exploded view 7472.0125-0130-0135 (2020)",
                "url": "https://www.combisteel.com/en/amfile/file/download/file/1236763/product/1336/"
            },
            {
                "label": "EU DECLARATION OF CONFORMITY 7472.0124-0125-0129-0130-0134-0135",
                "url": "https://www.combisteel.com/en/amfile/file/download/file/1236764/product/1336/"
            },
            {
                "label": "7472.0129-0130 dimensions",
                "url": "https://www.combisteel.com/en/amfile/file/download/file/1236765/product/1336/"
            }
        ],
        "accessories": [
            {
                "code": "7472.0138",
                "name": "MOUNTING SET 0124-0125-0129-0130-0134-0135",
                "url": "https://www.combisteel.com/en/7472-0138-mounting-set-0124-0125-0129-0130-0134-0135.html",
                "image": "https://www.combisteel.com/static/version20251021072834/frontend/H1/combisteel/en_GB/Magento_Catalog/images/product/placeholder/small_image.jpg",
                "image_large": "https://www.combisteel.com/static/version20251021072834/frontend/H1/combisteel/en_GB/Magento_Catalog/images/product/placeholder/small_image.jpg",
                "price": 3375,
                "price_currency": "CZK",
                "price_text": "3 375 Kč"
            },
            {
                "code": "7476.0225",
                "name": "ICE CREAM TRAY SS 5LTR",
                "url": "https://www.combisteel.com/en/7476-0225-ice-cream-tray-ss-5ltr.html",
                "image": "https://www.combisteel.com/media/catalog/product/cache/885770f149f21cca5edd4b51c2ad35e1/7/4/7476_0225-6514.jpg",
                "image_large": "https://www.combisteel.com/media/catalog/product/cache/885770f149f21cca5edd4b51c2ad35e1/7/4/7476_0225-6514.jpg",
                "price": 600,
                "price_currency": "CZK",
                "price_text": "600 Kč"
            },
            {
                "code": "7455.2020",
                "name": "ICE CREAM TRAY SS 5LTR",
                "url": "https://www.combisteel.com/en/7455-2020-ice-cream-tray-ss-5ltr.html",
                "image": "https://www.combisteel.com/static/version20251021072834/frontend/H1/combisteel/en_GB/Magento_Catalog/images/product/placeholder/small_image.jpg",
                "image_large": "https://www.combisteel.com/static/version20251021072834/frontend/H1/combisteel/en_GB/Magento_Catalog/images/product/placeholder/small_image.jpg",
                "price": 650,
                "price_currency": "CZK",
                "price_text": "650 Kč"
            }
        ]
    },
    {
        "code": "7472.0124",
        "name": "ICE CREAM DISPLAY CORISCA BLACK 6X5 LTR",
        "url": "https://www.combisteel.com/en/7472-0124-ice-cream-display-corisca-black-6x5-ltr.html",
        "image": "https://www.combisteel.com/media/catalog/product/cache/885770f149f21cca5edd4b51c2ad35e1/7/4/7472_0124.jpg",
        "image_large": "https://www.combisteel.com/media/catalog/product/cache/885770f149f21cca5edd4b51c2ad35e1/7/4/7472_0124.jpg",
        "price": 28375,
        "price_currency": "CZK",
        "price_text": "28 375 Kč",
        "specs": {
            "ean_code": 7422242973905,
            "width": 909,
            "depth": 684,
            "height": 1229,
            "color": "Black",
            "gross_weight": 71,
            "voltage": 230,
            "frequency": 50,
            "electrical_power": 0.19,
            "cooling_agent": "R 290",
            "capacity_in_units_per_time": "6x5 ltr",
            "temperature_range": "-24/-14",
            "gross_capacity": 231,
            "dim._interior_wxdxh": "785x520x688",
            "lights": "No",
            "type_of_cooling": "Static",
            "mobile": "Yes",
            "noise_level": 50,
            "under_cooling": "No",
            "defrost": "Manual",
            "max._ambient_temperature": 30,
            "power_consumption": 1.94,
            "brand": "COMBISTEEL",
            "refrigerant_quantity": "105 / 110",
            "energy_label": "A",
            "eprel_id": 1941380,
            "plug_and_play": "Yes"
        },
        "downloads": [
            {
                "label": "Energy label 7472.0124",
                "url": "https://www.combisteel.com/en/amfile/file/download/file/1216208/product/4672/"
            },
            {
                "label": "Manual 7472 Series ice cream displays",
                "url": "https://www.combisteel.com/en/amfile/file/download/file/1216209/product/4672/"
            },
            {
                "label": "Assembly Glass Cover 7472.0124-0125-0129-0130-0134-0135",
                "url": "https://www.combisteel.com/en/amfile/file/download/file/1216210/product/4672/"
            },
            {
                "label": "EU DECLARATION OF CONFORMITY 7472.0124-0125-0129-0130-0134-0135",
                "url": "https://www.combisteel.com/en/amfile/file/download/file/1216211/product/4672/"
            },
            {
                "label": "7472.0124-0125 dimensions",
                "url": "https://www.combisteel.com/en/amfile/file/download/file/1216212/product/4672/"
            },
            {
                "label": "Exploded view 7472.0124 (2025)",
                "url": "https://www.combisteel.com/en/amfile/file/download/file/1216213/product/4672/"
            }
        ],
        "accessories": [
            {
                "code": "7476.0225",
                "name": "ICE CREAM TRAY SS 5LTR",
                "url": "https://www.combisteel.com/en/7476-0225-ice-cream-tray-ss-5ltr.html",
                "image": "https://www.combisteel.com/media/catalog/product/cache/885770f149f21cca5edd4b51c2ad35e1/7/4/7476_0225-6514.jpg",
                "image_large": "https://www.combisteel.com/media/catalog/product/cache/885770f149f21cca5edd4b51c2ad35e1/7/4/7476_0225-6514.jpg",
                "price": 600,
                "price_currency": "CZK",
                "price_text": "600 Kč"
            },
            {
                "code": "7472.0138",
                "name": "MOUNTING SET 0124-0125-0129-0130-0134-0135",
                "url": "https://www.combisteel.com/en/7472-0138-mounting-set-0124-0125-0129-0130-0134-0135.html",
                "image": "https://www.combisteel.com/static/version20251021072834/frontend/H1/combisteel/en_GB/Magento_Catalog/images/product/placeholder/small_image.jpg",
                "image_large": "https://www.combisteel.com/static/version20251021072834/frontend/H1/combisteel/en_GB/Magento_Catalog/images/product/placeholder/small_image.jpg",
                "price": 3375,
                "price_currency": "CZK",
                "price_text": "3 375 Kč"
            },
            {
                "code": "7455.2020",
                "name": "ICE CREAM TRAY SS 5LTR",
                "url": "https://www.combisteel.com/en/7455-2020-ice-cream-tray-ss-5ltr.html",
                "image": "https://www.combisteel.com/static/version20251021072834/frontend/H1/combisteel/en_GB/Magento_Catalog/images/product/placeholder/small_image.jpg",
                "image_large": "https://www.combisteel.com/static/version20251021072834/frontend/H1/combisteel/en_GB/Magento_Catalog/images/product/placeholder/small_image.jpg",
                "price": 650,
                "price_currency": "CZK",
                "price_text": "650 Kč"
            }
        ]
    },
    {
        "code": "7472.0125",
        "name": "ICE CREAM DISPLAY CORISCA 6X5 LTR",
        "url": "https://www.combisteel.com/en/7472-0125-ice-cream-display-corisca-6x5-ltr.html",
        "image": "https://www.combisteel.com/media/catalog/product/cache/885770f149f21cca5edd4b51c2ad35e1/7/4/7472_0125-7592_2.jpg",
        "image_large": "https://www.combisteel.com/media/catalog/product/cache/885770f149f21cca5edd4b51c2ad35e1/7/4/7472_0125-7592_2.jpg",
        "price": 27875,
        "price_currency": "CZK",
        "price_text": "27 875 Kč",
        "specs": {
            "ean_code": 7435137797784,
            "width": 909,
            "depth": 684,
            "height": 1229,
            "color": "White",
            "gross_weight": 71,
            "voltage": 230,
            "frequency": 50,
            "electrical_power": 0.19,
            "cooling_agent": "R 290",
            "capacity_in_units_per_time": "6x5 ltr",
            "temperature_range": "-24/-14",
            "gross_capacity": 231,
            "dim._interior_wxdxh": "785x520x688",
            "lights": "No",
            "type_of_cooling": "Static",
            "mobile": "Yes",
            "noise_level": 50,
            "under_cooling": "No",
            "defrost": "Manual",
            "max._ambient_temperature": 30,
            "power_consumption": 1.94,
            "brand": "COMBISTEEL",
            "refrigerant_quantity": "105 / 110",
            "energy_label": "A",
            "eprel_id": 1941392,
            "plug_and_play": "Yes"
        },
        "downloads": [
            {
                "label": "Energy label 7472.0125",
                "url": "https://www.combisteel.com/en/amfile/file/download/file/1232356/product/1334/"
            },
            {
                "label": "Manual 7472 Series ice cream displays",
                "url": "https://www.combisteel.com/en/amfile/file/download/file/1232357/product/1334/"
            },
            {
                "label": "Assembly Glass Cover 7472.0124-0125-0129-0130-0134-0135",
                "url": "https://www.combisteel.com/en/amfile/file/download/file/1232358/product/1334/"
            },
            {
                "label": "Exploded view 7472.0125-0130-0135 (2020)",
                "url": "https://www.combisteel.com/en/amfile/file/download/file/1232359/product/1334/"
            },
            {
                "label": "EU DECLARATION OF CONFORMITY 7472.0124-0125-0129-0130-0134-0135",
                "url": "https://www.combisteel.com/en/amfile/file/download/file/1232360/product/1334/"
            },
            {
                "label": "7472.0124-0125 dimensions",
                "url": "https://www.combisteel.com/en/amfile/file/download/file/1232361/product/1334/"
            }
        ],
        "accessories": [
            {
                "code": "7476.0225",
                "name": "ICE CREAM TRAY SS 5LTR",
                "url": "https://www.combisteel.com/en/7476-0225-ice-cream-tray-ss-5ltr.html",
                "image": "https://www.combisteel.com/media/catalog/product/cache/885770f149f21cca5edd4b51c2ad35e1/7/4/7476_0225-6514.jpg",
                "image_large": "https://www.combisteel.com/media/catalog/product/cache/885770f149f21cca5edd4b51c2ad35e1/7/4/7476_0225-6514.jpg",
                "price": 600,
                "price_currency": "CZK",
                "price_text": "600 Kč"
            },
            {
                "code": "7472.0138",
                "name": "MOUNTING SET 0124-0125-0129-0130-0134-0135",
                "url": "https://www.combisteel.com/en/7472-0138-mounting-set-0124-0125-0129-0130-0134-0135.html",
                "image": "https://www.combisteel.com/static/version20251021072834/frontend/H1/combisteel/en_GB/Magento_Catalog/images/product/placeholder/small_image.jpg",
                "image_large": "https://www.combisteel.com/static/version20251021072834/frontend/H1/combisteel/en_GB/Magento_Catalog/images/product/placeholder/small_image.jpg",
                "price": 3375,
                "price_currency": "CZK",
                "price_text": "3 375 Kč"
            },
            {
                "code": "7455.2020",
                "name": "ICE CREAM TRAY SS 5LTR",
                "url": "https://www.combisteel.com/en/7455-2020-ice-cream-tray-ss-5ltr.html",
                "image": "https://www.combisteel.com/static/version20251021072834/frontend/H1/combisteel/en_GB/Magento_Catalog/images/product/placeholder/small_image.jpg",
                "image_large": "https://www.combisteel.com/static/version20251021072834/frontend/H1/combisteel/en_GB/Magento_Catalog/images/product/placeholder/small_image.jpg",
                "price": 650,
                "price_currency": "CZK",
                "price_text": "650 Kč"
            }
        ]
    }
]